[{"span": "year", "quote": "https://api.robinhood.com/quotes/f8122a27-037e-4d17-be98-becdc737fe42/", "symbol": "BMLP", "interval": "day", "historicals": [{"high_price": "52.3200", "interpolated": false, "low_price": "52.3200", "begins_at": "2017-03-28T00:00:00Z", "volume": 0, "session": "reg", "open_price": "52.3200", "close_price": "52.3200"}, {"high_price": "52.3200", "interpolated": false, "low_price": "52.3200", "begins_at": "2017-03-29T00:00:00Z", "volume": 0, "session": "reg", "open_price": "52.3200", "close_price": "52.3200"}, {"high_price": "53.0600", "interpolated": false, "low_price": "53.0600", "begins_at": "2017-03-30T00:00:00Z", "volume": 100, "session": "reg", "open_price": "53.0600", "close_price": "53.0600"}, {"high_price": "53.0600", "interpolated": false, "low_price": "53.0600", "begins_at": "2017-03-31T00:00:00Z", "volume": 0, "session": "reg", "open_price": "53.0600", "close_price": "53.0600"}, {"high_price": "53.0600", "interpolated": false, "low_price": "53.0600", "begins_at": "2017-04-03T00:00:00Z", "volume": 0, "session": "reg", "open_price": "53.0600", "close_price": "53.0600"}, {"high_price": "53.0600", "interpolated": false, "low_price": "53.0600", "begins_at": "2017-04-04T00:00:00Z", "volume": 0, "session": "reg", "open_price": "53.0600", "close_price": "53.0600"}, {"high_price": "53.0600", "interpolated": false, "low_price": "53.0600", "begins_at": "2017-04-05T00:00:00Z", "volume": 0, "session": "reg", "open_price": "53.0600", "close_price": "53.0600"}, {"high_price": "53.0600", "interpolated": false, "low_price": "53.0600", "begins_at": "2017-04-06T00:00:00Z", "volume": 0, "session": "reg", "open_price": "53.0600", "close_price": "53.0600"}, {"high_price": "53.0600", "interpolated": false, "low_price": "53.0600", "begins_at": "2017-04-07T00:00:00Z", "volume": 0, "session": "reg", "open_price": "53.0600", "close_price": "53.0600"}, {"high_price": "53.0600", "interpolated": false, "low_price": "53.0600", "begins_at": "2017-04-10T00:00:00Z", "volume": 0, "session": "reg", "open_price": "53.0600", "close_price": "53.0600"}, {"high_price": "53.0600", "interpolated": false, "low_price": "53.0600", "begins_at": "2017-04-11T00:00:00Z", "volume": 0, "session": "reg", "open_price": "53.0600", "close_price": "53.0600"}, {"high_price": "53.0600", "interpolated": false, "low_price": "53.0600", "begins_at": "2017-04-12T00:00:00Z", "volume": 0, "session": "reg", "open_price": "53.0600", "close_price": "53.0600"}, {"high_price": "53.0600", "interpolated": false, "low_price": "53.0600", "begins_at": "2017-04-13T00:00:00Z", "volume": 0, "session": "reg", "open_price": "53.0600", "close_price": "53.0600"}, {"high_price": "53.0600", "interpolated": false, "low_price": "53.0600", "begins_at": "2017-04-17T00:00:00Z", "volume": 0, "session": "reg", "open_price": "53.0600", "close_price": "53.0600"}, {"high_price": "53.0600", "interpolated": false, "low_price": "53.0600", "begins_at": "2017-04-18T00:00:00Z", "volume": 0, "session": "reg", "open_price": "53.0600", "close_price": "53.0600"}, {"high_price": "53.0600", "interpolated": false, "low_price": "53.0600", "begins_at": "2017-04-19T00:00:00Z", "volume": 0, "session": "reg", "open_price": "53.0600", "close_price": "53.0600"}, {"high_price": "53.0600", "interpolated": false, "low_price": "53.0600", "begins_at": "2017-04-20T00:00:00Z", "volume": 50, "session": "reg", "open_price": "53.0600", "close_price": "53.0600"}, {"high_price": "52.2999", "interpolated": false, "low_price": "52.2999", "begins_at": "2017-04-21T00:00:00Z", "volume": 136, "session": "reg", "open_price": "52.2999", "close_price": "52.2999"}, {"high_price": "53.0800", "interpolated": false, "low_price": "53.0800", "begins_at": "2017-04-24T00:00:00Z", "volume": 100, "session": "reg", "open_price": "53.0800", "close_price": "53.0800"}, {"high_price": "52.6700", "interpolated": false, "low_price": "52.6700", "begins_at": "2017-04-25T00:00:00Z", "volume": 200, "session": "reg", "open_price": "52.6700", "close_price": "52.6700"}, {"high_price": "52.6700", "interpolated": false, "low_price": "52.6700", "begins_at": "2017-04-26T00:00:00Z", "volume": 0, "session": "reg", "open_price": "52.6700", "close_price": "52.6700"}, {"high_price": "51.9400", "interpolated": false, "low_price": "51.9400", "begins_at": "2017-04-27T00:00:00Z", "volume": 300, "session": "reg", "open_price": "51.9400", "close_price": "51.9400"}, {"high_price": "51.9200", "interpolated": false, "low_price": "51.9200", "begins_at": "2017-04-28T00:00:00Z", "volume": 100, "session": "reg", "open_price": "51.9200", "close_price": "51.9200"}, {"high_price": "51.9200", "interpolated": false, "low_price": "51.9200", "begins_at": "2017-05-01T00:00:00Z", "volume": 0, "session": "reg", "open_price": "51.9200", "close_price": "51.9200"}, {"high_price": "51.9200", "interpolated": false, "low_price": "51.9200", "begins_at": "2017-05-02T00:00:00Z", "volume": 18, "session": "reg", "open_price": "51.9200", "close_price": "51.9200"}, {"high_price": "51.8600", "interpolated": false, "low_price": "51.8400", "begins_at": "2017-05-03T00:00:00Z", "volume": 6600, "session": "reg", "open_price": "51.8600", "close_price": "51.8400"}, {"high_price": "51.8400", "interpolated": false, "low_price": "51.8400", "begins_at": "2017-05-04T00:00:00Z", "volume": 0, "session": "reg", "open_price": "51.8400", "close_price": "51.8400"}, {"high_price": "51.8400", "interpolated": false, "low_price": "51.8400", "begins_at": "2017-05-05T00:00:00Z", "volume": 0, "session": "reg", "open_price": "51.8400", "close_price": "51.8400"}, {"high_price": "51.8400", "interpolated": false, "low_price": "51.8400", "begins_at": "2017-05-08T00:00:00Z", "volume": 0, "session": "reg", "open_price": "51.8400", "close_price": "51.8400"}, {"high_price": "51.8400", "interpolated": false, "low_price": "51.8400", "begins_at": "2017-05-09T00:00:00Z", "volume": 44, "session": "reg", "open_price": "51.8400", "close_price": "51.8400"}, {"high_price": "51.8400", "interpolated": false, "low_price": "51.8400", "begins_at": "2017-05-10T00:00:00Z", "volume": 0, "session": "reg", "open_price": "51.8400", "close_price": "51.8400"}, {"high_price": "51.8400", "interpolated": false, "low_price": "51.8400", "begins_at": "2017-05-11T00:00:00Z", "volume": 0, "session": "reg", "open_price": "51.8400", "close_price": "51.8400"}, {"high_price": "51.8400", "interpolated": false, "low_price": "51.8400", "begins_at": "2017-05-12T00:00:00Z", "volume": 0, "session": "reg", "open_price": "51.8400", "close_price": "51.8400"}, {"high_price": "51.8400", "interpolated": false, "low_price": "51.8400", "begins_at": "2017-05-15T00:00:00Z", "volume": 0, "session": "reg", "open_price": "51.8400", "close_price": "51.8400"}, {"high_price": "52.1600", "interpolated": false, "low_price": "52.1600", "begins_at": "2017-05-16T00:00:00Z", "volume": 16755, "session": "reg", "open_price": "52.1600", "close_price": "52.1600"}, {"high_price": "52.1600", "interpolated": false, "low_price": "52.1600", "begins_at": "2017-05-17T00:00:00Z", "volume": 0, "session": "reg", "open_price": "52.1600", "close_price": "52.1600"}, {"high_price": "51.0279", "interpolated": false, "low_price": "51.0279", "begins_at": "2017-05-18T00:00:00Z", "volume": 206, "session": "reg", "open_price": "51.0279", "close_price": "51.0279"}, {"high_price": "51.0279", "interpolated": false, "low_price": "51.0279", "begins_at": "2017-05-19T00:00:00Z", "volume": 0, "session": "reg", "open_price": "51.0279", "close_price": "51.0279"}, {"high_price": "51.0279", "interpolated": false, "low_price": "51.0279", "begins_at": "2017-05-22T00:00:00Z", "volume": 0, "session": "reg", "open_price": "51.0279", "close_price": "51.0279"}, {"high_price": "51.0279", "interpolated": false, "low_price": "51.0279", "begins_at": "2017-05-23T00:00:00Z", "volume": 0, "session": "reg", "open_price": "51.0279", "close_price": "51.0279"}, {"high_price": "51.0279", "interpolated": false, "low_price": "51.0279", "begins_at": "2017-05-24T00:00:00Z", "volume": 75, "session": "reg", "open_price": "51.0279", "close_price": "51.0279"}, {"high_price": "52.0900", "interpolated": false, "low_price": "52.0900", "begins_at": "2017-05-25T00:00:00Z", "volume": 122, "session": "reg", "open_price": "52.0900", "close_price": "52.0900"}, {"high_price": "51.7200", "interpolated": false, "low_price": "51.7200", "begins_at": "2017-05-26T00:00:00Z", "volume": 100, "session": "reg", "open_price": "51.7200", "close_price": "51.7200"}, {"high_price": "51.7200", "interpolated": false, "low_price": "51.7200", "begins_at": "2017-05-30T00:00:00Z", "volume": 0, "session": "reg", "open_price": "51.7200", "close_price": "51.7200"}, {"high_price": "50.0500", "interpolated": false, "low_price": "49.7200", "begins_at": "2017-05-31T00:00:00Z", "volume": 295, "session": "reg", "open_price": "50.0500", "close_price": "49.7200"}, {"high_price": "49.7200", "interpolated": false, "low_price": "49.7200", "begins_at": "2017-06-01T00:00:00Z", "volume": 50, "session": "reg", "open_price": "49.7200", "close_price": "49.7200"}, {"high_price": "49.7200", "interpolated": false, "low_price": "49.7200", "begins_at": "2017-06-02T00:00:00Z", "volume": 0, "session": "reg", "open_price": "49.7200", "close_price": "49.7200"}, {"high_price": "49.7200", "interpolated": false, "low_price": "49.7200", "begins_at": "2017-06-05T00:00:00Z", "volume": 0, "session": "reg", "open_price": "49.7200", "close_price": "49.7200"}, {"high_price": "49.7200", "interpolated": false, "low_price": "49.7200", "begins_at": "2017-06-06T00:00:00Z", "volume": 0, "session": "reg", "open_price": "49.7200", "close_price": "49.7200"}, {"high_price": "49.3899", "interpolated": false, "low_price": "49.3899", "begins_at": "2017-06-07T00:00:00Z", "volume": 325, "session": "reg", "open_price": "49.3899", "close_price": "49.3899"}, {"high_price": "49.3899", "interpolated": false, "low_price": "49.3899", "begins_at": "2017-06-08T00:00:00Z", "volume": 0, "session": "reg", "open_price": "49.3899", "close_price": "49.3899"}, {"high_price": "49.3899", "interpolated": false, "low_price": "49.3899", "begins_at": "2017-06-09T00:00:00Z", "volume": 0, "session": "reg", "open_price": "49.3899", "close_price": "49.3899"}, {"high_price": "49.3899", "interpolated": false, "low_price": "49.3899", "begins_at": "2017-06-12T00:00:00Z", "volume": 0, "session": "reg", "open_price": "49.3899", "close_price": "49.3899"}, {"high_price": "49.3899", "interpolated": false, "low_price": "49.3899", "begins_at": "2017-06-13T00:00:00Z", "volume": 0, "session": "reg", "open_price": "49.3899", "close_price": "49.3899"}, {"high_price": "48.4800", "interpolated": false, "low_price": "48.4799", "begins_at": "2017-06-14T00:00:00Z", "volume": 340, "session": "reg", "open_price": "48.4799", "close_price": "48.4800"}, {"high_price": "48.4800", "interpolated": false, "low_price": "48.4800", "begins_at": "2017-06-15T00:00:00Z", "volume": 44, "session": "reg", "open_price": "48.4800", "close_price": "48.4800"}, {"high_price": "48.4800", "interpolated": false, "low_price": "48.4800", "begins_at": "2017-06-16T00:00:00Z", "volume": 0, "session": "reg", "open_price": "48.4800", "close_price": "48.4800"}, {"high_price": "48.4800", "interpolated": false, "low_price": "48.4800", "begins_at": "2017-06-19T00:00:00Z", "volume": 0, "session": "reg", "open_price": "48.4800", "close_price": "48.4800"}, {"high_price": "48.4800", "interpolated": false, "low_price": "48.4800", "begins_at": "2017-06-20T00:00:00Z", "volume": 0, "session": "reg", "open_price": "48.4800", "close_price": "48.4800"}, {"high_price": "45.7200", "interpolated": false, "low_price": "45.7200", "begins_at": "2017-06-21T00:00:00Z", "volume": 155, "session": "reg", "open_price": "45.7200", "close_price": "45.7200"}, {"high_price": "45.7200", "interpolated": false, "low_price": "45.7200", "begins_at": "2017-06-22T00:00:00Z", "volume": 18, "session": "reg", "open_price": "45.7200", "close_price": "45.7200"}, {"high_price": "45.7200", "interpolated": false, "low_price": "45.7200", "begins_at": "2017-06-23T00:00:00Z", "volume": 37, "session": "reg", "open_price": "45.7200", "close_price": "45.7200"}, {"high_price": "45.7200", "interpolated": false, "low_price": "45.7200", "begins_at": "2017-06-26T00:00:00Z", "volume": 0, "session": "reg", "open_price": "45.7200", "close_price": "45.7200"}, {"high_price": "45.7200", "interpolated": false, "low_price": "45.7200", "begins_at": "2017-06-27T00:00:00Z", "volume": 0, "session": "reg", "open_price": "45.7200", "close_price": "45.7200"}, {"high_price": "47.7500", "interpolated": false, "low_price": "47.7500", "begins_at": "2017-06-28T00:00:00Z", "volume": 108, "session": "reg", "open_price": "47.7500", "close_price": "47.7500"}, {"high_price": "47.7500", "interpolated": false, "low_price": "47.7500", "begins_at": "2017-06-29T00:00:00Z", "volume": 0, "session": "reg", "open_price": "47.7500", "close_price": "47.7500"}, {"high_price": "47.7500", "interpolated": false, "low_price": "47.7500", "begins_at": "2017-06-30T00:00:00Z", "volume": 0, "session": "reg", "open_price": "47.7500", "close_price": "47.7500"}, {"high_price": "47.7500", "interpolated": false, "low_price": "47.7500", "begins_at": "2017-07-05T00:00:00Z", "volume": 0, "session": "reg", "open_price": "47.7500", "close_price": "47.7500"}, {"high_price": "47.7500", "interpolated": false, "low_price": "47.7500", "begins_at": "2017-07-06T00:00:00Z", "volume": 0, "session": "reg", "open_price": "47.7500", "close_price": "47.7500"}, {"high_price": "47.7500", "interpolated": false, "low_price": "47.7500", "begins_at": "2017-07-07T00:00:00Z", "volume": 0, "session": "reg", "open_price": "47.7500", "close_price": "47.7500"}, {"high_price": "47.7500", "interpolated": false, "low_price": "47.7500", "begins_at": "2017-07-10T00:00:00Z", "volume": 0, "session": "reg", "open_price": "47.7500", "close_price": "47.7500"}, {"high_price": "47.7500", "interpolated": false, "low_price": "47.7500", "begins_at": "2017-07-11T00:00:00Z", "volume": 0, "session": "reg", "open_price": "47.7500", "close_price": "47.7500"}, {"high_price": "47.7500", "interpolated": false, "low_price": "47.7500", "begins_at": "2017-07-12T00:00:00Z", "volume": 0, "session": "reg", "open_price": "47.7500", "close_price": "47.7500"}, {"high_price": "47.7500", "interpolated": false, "low_price": "47.7500", "begins_at": "2017-07-13T00:00:00Z", "volume": 0, "session": "reg", "open_price": "47.7500", "close_price": "47.7500"}, {"high_price": "47.7500", "interpolated": false, "low_price": "47.7500", "begins_at": "2017-07-14T00:00:00Z", "volume": 13, "session": "reg", "open_price": "47.7500", "close_price": "47.7500"}, {"high_price": "49.3500", "interpolated": false, "low_price": "49.3500", "begins_at": "2017-07-17T00:00:00Z", "volume": 175, "session": "reg", "open_price": "49.3500", "close_price": "49.3500"}, {"high_price": "49.3500", "interpolated": false, "low_price": "49.3500", "begins_at": "2017-07-18T00:00:00Z", "volume": 0, "session": "reg", "open_price": "49.3500", "close_price": "49.3500"}, {"high_price": "49.4432", "interpolated": false, "low_price": "49.4300", "begins_at": "2017-07-19T00:00:00Z", "volume": 644, "session": "reg", "open_price": "49.4310", "close_price": "49.4432"}, {"high_price": "49.4432", "interpolated": false, "low_price": "49.4432", "begins_at": "2017-07-20T00:00:00Z", "volume": 0, "session": "reg", "open_price": "49.4432", "close_price": "49.4432"}, {"high_price": "49.4432", "interpolated": false, "low_price": "49.4432", "begins_at": "2017-07-21T00:00:00Z", "volume": 1, "session": "reg", "open_price": "49.4432", "close_price": "49.4432"}, {"high_price": "48.8040", "interpolated": false, "low_price": "48.7701", "begins_at": "2017-07-24T00:00:00Z", "volume": 313, "session": "reg", "open_price": "48.8040", "close_price": "48.7701"}, {"high_price": "48.7701", "interpolated": false, "low_price": "48.7701", "begins_at": "2017-07-25T00:00:00Z", "volume": 0, "session": "reg", "open_price": "48.7701", "close_price": "48.7701"}, {"high_price": "48.7701", "interpolated": false, "low_price": "48.7701", "begins_at": "2017-07-26T00:00:00Z", "volume": 0, "session": "reg", "open_price": "48.7701", "close_price": "48.7701"}, {"high_price": "48.7701", "interpolated": false, "low_price": "48.7701", "begins_at": "2017-07-27T00:00:00Z", "volume": 0, "session": "reg", "open_price": "48.7701", "close_price": "48.7701"}, {"high_price": "48.7701", "interpolated": false, "low_price": "48.7701", "begins_at": "2017-07-28T00:00:00Z", "volume": 0, "session": "reg", "open_price": "48.7701", "close_price": "48.7701"}, {"high_price": "48.7701", "interpolated": false, "low_price": "48.7701", "begins_at": "2017-07-31T00:00:00Z", "volume": 92, "session": "reg", "open_price": "48.7701", "close_price": "48.7701"}, {"high_price": "48.7701", "interpolated": false, "low_price": "48.7701", "begins_at": "2017-08-01T00:00:00Z", "volume": 7, "session": "reg", "open_price": "48.7701", "close_price": "48.7701"}, {"high_price": "48.7701", "interpolated": false, "low_price": "48.7701", "begins_at": "2017-08-02T00:00:00Z", "volume": 0, "session": "reg", "open_price": "48.7701", "close_price": "48.7701"}, {"high_price": "49.9000", "interpolated": false, "low_price": "49.7000", "begins_at": "2017-08-03T00:00:00Z", "volume": 405, "session": "reg", "open_price": "49.9000", "close_price": "49.7000"}, {"high_price": "49.7000", "interpolated": false, "low_price": "49.7000", "begins_at": "2017-08-04T00:00:00Z", "volume": 0, "session": "reg", "open_price": "49.7000", "close_price": "49.7000"}, {"high_price": "49.7000", "interpolated": false, "low_price": "49.7000", "begins_at": "2017-08-07T00:00:00Z", "volume": 5, "session": "reg", "open_price": "49.7000", "close_price": "49.7000"}, {"high_price": "49.7000", "interpolated": false, "low_price": "49.7000", "begins_at": "2017-08-08T00:00:00Z", "volume": 0, "session": "reg", "open_price": "49.7000", "close_price": "49.7000"}, {"high_price": "49.7000", "interpolated": false, "low_price": "49.7000", "begins_at": "2017-08-09T00:00:00Z", "volume": 20, "session": "reg", "open_price": "49.7000", "close_price": "49.7000"}, {"high_price": "49.7000", "interpolated": false, "low_price": "49.7000", "begins_at": "2017-08-10T00:00:00Z", "volume": 0, "session": "reg", "open_price": "49.7000", "close_price": "49.7000"}, {"high_price": "49.7000", "interpolated": false, "low_price": "49.7000", "begins_at": "2017-08-11T00:00:00Z", "volume": 0, "session": "reg", "open_price": "49.7000", "close_price": "49.7000"}, {"high_price": "49.7000", "interpolated": false, "low_price": "49.7000", "begins_at": "2017-08-14T00:00:00Z", "volume": 1, "session": "reg", "open_price": "49.7000", "close_price": "49.7000"}, {"high_price": "49.7000", "interpolated": false, "low_price": "49.7000", "begins_at": "2017-08-15T00:00:00Z", "volume": 0, "session": "reg", "open_price": "49.7000", "close_price": "49.7000"}, {"high_price": "49.7000", "interpolated": false, "low_price": "49.7000", "begins_at": "2017-08-16T00:00:00Z", "volume": 0, "session": "reg", "open_price": "49.7000", "close_price": "49.7000"}, {"high_price": "49.7000", "interpolated": false, "low_price": "49.7000", "begins_at": "2017-08-17T00:00:00Z", "volume": 0, "session": "reg", "open_price": "49.7000", "close_price": "49.7000"}, {"high_price": "49.7000", "interpolated": false, "low_price": "49.7000", "begins_at": "2017-08-18T00:00:00Z", "volume": 0, "session": "reg", "open_price": "49.7000", "close_price": "49.7000"}, {"high_price": "49.7000", "interpolated": false, "low_price": "49.7000", "begins_at": "2017-08-21T00:00:00Z", "volume": 0, "session": "reg", "open_price": "49.7000", "close_price": "49.7000"}, {"high_price": "49.7000", "interpolated": false, "low_price": "49.7000", "begins_at": "2017-08-22T00:00:00Z", "volume": 0, "session": "reg", "open_price": "49.7000", "close_price": "49.7000"}, {"high_price": "49.7000", "interpolated": false, "low_price": "49.7000", "begins_at": "2017-08-23T00:00:00Z", "volume": 0, "session": "reg", "open_price": "49.7000", "close_price": "49.7000"}, {"high_price": "49.7000", "interpolated": false, "low_price": "49.7000", "begins_at": "2017-08-24T00:00:00Z", "volume": 0, "session": "reg", "open_price": "49.7000", "close_price": "49.7000"}, {"high_price": "49.7000", "interpolated": false, "low_price": "49.7000", "begins_at": "2017-08-25T00:00:00Z", "volume": 0, "session": "reg", "open_price": "49.7000", "close_price": "49.7000"}, {"high_price": "46.6000", "interpolated": false, "low_price": "46.5008", "begins_at": "2017-08-28T00:00:00Z", "volume": 399, "session": "reg", "open_price": "46.5812", "close_price": "46.6000"}, {"high_price": "46.6000", "interpolated": false, "low_price": "46.6000", "begins_at": "2017-08-29T00:00:00Z", "volume": 100, "session": "reg", "open_price": "46.6000", "close_price": "46.6000"}, {"high_price": "46.6000", "interpolated": false, "low_price": "46.6000", "begins_at": "2017-08-30T00:00:00Z", "volume": 0, "session": "reg", "open_price": "46.6000", "close_price": "46.6000"}, {"high_price": "47.8800", "interpolated": false, "low_price": "47.8605", "begins_at": "2017-08-31T00:00:00Z", "volume": 470, "session": "reg", "open_price": "47.8799", "close_price": "47.8800"}, {"high_price": "47.7400", "interpolated": false, "low_price": "47.7212", "begins_at": "2017-09-01T00:00:00Z", "volume": 470, "session": "reg", "open_price": "47.7399", "close_price": "47.7400"}, {"high_price": "47.7400", "interpolated": false, "low_price": "47.7400", "begins_at": "2017-09-05T00:00:00Z", "volume": 0, "session": "reg", "open_price": "47.7400", "close_price": "47.7400"}, {"high_price": "47.9000", "interpolated": false, "low_price": "47.5859", "begins_at": "2017-09-06T00:00:00Z", "volume": 2606, "session": "reg", "open_price": "47.6600", "close_price": "47.8400"}, {"high_price": "47.8400", "interpolated": false, "low_price": "47.8400", "begins_at": "2017-09-07T00:00:00Z", "volume": 124, "session": "reg", "open_price": "47.8400", "close_price": "47.8400"}, {"high_price": "47.8400", "interpolated": false, "low_price": "47.8400", "begins_at": "2017-09-08T00:00:00Z", "volume": 0, "session": "reg", "open_price": "47.8400", "close_price": "47.8400"}, {"high_price": "47.6864", "interpolated": false, "low_price": "47.6864", "begins_at": "2017-09-11T00:00:00Z", "volume": 175, "session": "reg", "open_price": "47.6864", "close_price": "47.6864"}, {"high_price": "47.7000", "interpolated": false, "low_price": "47.5900", "begins_at": "2017-09-12T00:00:00Z", "volume": 335, "session": "reg", "open_price": "47.5900", "close_price": "47.7000"}, {"high_price": "47.7000", "interpolated": false, "low_price": "47.7000", "begins_at": "2017-09-13T00:00:00Z", "volume": 1, "session": "reg", "open_price": "47.7000", "close_price": "47.7000"}, {"high_price": "47.7000", "interpolated": false, "low_price": "47.7000", "begins_at": "2017-09-14T00:00:00Z", "volume": 0, "session": "reg", "open_price": "47.7000", "close_price": "47.7000"}, {"high_price": "47.7000", "interpolated": false, "low_price": "47.7000", "begins_at": "2017-09-15T00:00:00Z", "volume": 73, "session": "reg", "open_price": "47.7000", "close_price": "47.7000"}, {"high_price": "47.7000", "interpolated": false, "low_price": "47.7000", "begins_at": "2017-09-18T00:00:00Z", "volume": 0, "session": "reg", "open_price": "47.7000", "close_price": "47.7000"}, {"high_price": "47.7000", "interpolated": false, "low_price": "47.7000", "begins_at": "2017-09-19T00:00:00Z", "volume": 0, "session": "reg", "open_price": "47.7000", "close_price": "47.7000"}, {"high_price": "47.7000", "interpolated": false, "low_price": "47.7000", "begins_at": "2017-09-20T00:00:00Z", "volume": 0, "session": "reg", "open_price": "47.7000", "close_price": "47.7000"}, {"high_price": "47.7000", "interpolated": false, "low_price": "47.7000", "begins_at": "2017-09-21T00:00:00Z", "volume": 73, "session": "reg", "open_price": "47.7000", "close_price": "47.7000"}, {"high_price": "47.7000", "interpolated": false, "low_price": "47.7000", "begins_at": "2017-09-22T00:00:00Z", "volume": 0, "session": "reg", "open_price": "47.7000", "close_price": "47.7000"}, {"high_price": "47.4004", "interpolated": false, "low_price": "47.4004", "begins_at": "2017-09-25T00:00:00Z", "volume": 230, "session": "reg", "open_price": "47.4004", "close_price": "47.4004"}, {"high_price": "47.4000", "interpolated": false, "low_price": "47.3500", "begins_at": "2017-09-26T00:00:00Z", "volume": 950, "session": "reg", "open_price": "47.3800", "close_price": "47.4000"}, {"high_price": "47.4000", "interpolated": false, "low_price": "47.4000", "begins_at": "2017-09-27T00:00:00Z", "volume": 0, "session": "reg", "open_price": "47.4000", "close_price": "47.4000"}, {"high_price": "47.4000", "interpolated": false, "low_price": "47.4000", "begins_at": "2017-09-28T00:00:00Z", "volume": 0, "session": "reg", "open_price": "47.4000", "close_price": "47.4000"}, {"high_price": "47.4000", "interpolated": false, "low_price": "47.4000", "begins_at": "2017-09-29T00:00:00Z", "volume": 50, "session": "reg", "open_price": "47.4000", "close_price": "47.4000"}, {"high_price": "47.2718", "interpolated": false, "low_price": "47.2718", "begins_at": "2017-10-02T00:00:00Z", "volume": 236, "session": "reg", "open_price": "47.2718", "close_price": "47.2718"}, {"high_price": "47.2718", "interpolated": false, "low_price": "47.2718", "begins_at": "2017-10-03T00:00:00Z", "volume": 1, "session": "reg", "open_price": "47.2718", "close_price": "47.2718"}, {"high_price": "47.2718", "interpolated": false, "low_price": "47.2718", "begins_at": "2017-10-04T00:00:00Z", "volume": 0, "session": "reg", "open_price": "47.2718", "close_price": "47.2718"}, {"high_price": "47.2718", "interpolated": false, "low_price": "47.2718", "begins_at": "2017-10-05T00:00:00Z", "volume": 0, "session": "reg", "open_price": "47.2718", "close_price": "47.2718"}, {"high_price": "47.8799", "interpolated": false, "low_price": "47.8680", "begins_at": "2017-10-06T00:00:00Z", "volume": 297, "session": "reg", "open_price": "47.8799", "close_price": "47.8680"}, {"high_price": "47.8680", "interpolated": false, "low_price": "47.8680", "begins_at": "2017-10-09T00:00:00Z", "volume": 1, "session": "reg", "open_price": "47.8680", "close_price": "47.8680"}, {"high_price": "47.8680", "interpolated": false, "low_price": "47.8680", "begins_at": "2017-10-10T00:00:00Z", "volume": 0, "session": "reg", "open_price": "47.8680", "close_price": "47.8680"}, {"high_price": "47.8680", "interpolated": false, "low_price": "47.8680", "begins_at": "2017-10-11T00:00:00Z", "volume": 0, "session": "reg", "open_price": "47.8680", "close_price": "47.8680"}, {"high_price": "47.8680", "interpolated": false, "low_price": "47.8680", "begins_at": "2017-10-12T00:00:00Z", "volume": 0, "session": "reg", "open_price": "47.8680", "close_price": "47.8680"}, {"high_price": "47.5068", "interpolated": false, "low_price": "47.4400", "begins_at": "2017-10-13T00:00:00Z", "volume": 650, "session": "reg", "open_price": "47.4401", "close_price": "47.4400"}, {"high_price": "47.4400", "interpolated": false, "low_price": "47.4400", "begins_at": "2017-10-16T00:00:00Z", "volume": 2, "session": "reg", "open_price": "47.4400", "close_price": "47.4400"}, {"high_price": "47.2000", "interpolated": false, "low_price": "47.0465", "begins_at": "2017-10-17T00:00:00Z", "volume": 937, "session": "reg", "open_price": "47.1035", "close_price": "47.0465"}, {"high_price": "47.0465", "interpolated": false, "low_price": "47.0465", "begins_at": "2017-10-18T00:00:00Z", "volume": 0, "session": "reg", "open_price": "47.0465", "close_price": "47.0465"}, {"high_price": "46.2400", "interpolated": false, "low_price": "46.2400", "begins_at": "2017-10-19T00:00:00Z", "volume": 100, "session": "reg", "open_price": "46.2400", "close_price": "46.2400"}, {"high_price": "46.5400", "interpolated": false, "low_price": "46.5275", "begins_at": "2017-10-20T00:00:00Z", "volume": 712, "session": "reg", "open_price": "46.5399", "close_price": "46.5275"}, {"high_price": "46.3000", "interpolated": false, "low_price": "46.0700", "begins_at": "2017-10-23T00:00:00Z", "volume": 325, "session": "reg", "open_price": "46.3000", "close_price": "46.0700"}, {"high_price": "46.0700", "interpolated": false, "low_price": "46.0700", "begins_at": "2017-10-24T00:00:00Z", "volume": 7, "session": "reg", "open_price": "46.0700", "close_price": "46.0700"}, {"high_price": "46.0700", "interpolated": false, "low_price": "46.0700", "begins_at": "2017-10-25T00:00:00Z", "volume": 0, "session": "reg", "open_price": "46.0700", "close_price": "46.0700"}, {"high_price": "45.6700", "interpolated": false, "low_price": "45.3500", "begins_at": "2017-10-26T00:00:00Z", "volume": 1817, "session": "reg", "open_price": "45.3500", "close_price": "45.5619"}, {"high_price": "45.5619", "interpolated": false, "low_price": "45.5619", "begins_at": "2017-10-27T00:00:00Z", "volume": 0, "session": "reg", "open_price": "45.5619", "close_price": "45.5619"}, {"high_price": "45.9600", "interpolated": false, "low_price": "45.9600", "begins_at": "2017-10-30T00:00:00Z", "volume": 125, "session": "reg", "open_price": "45.9600", "close_price": "45.9600"}, {"high_price": "46.1300", "interpolated": false, "low_price": "46.0501", "begins_at": "2017-10-31T00:00:00Z", "volume": 802, "session": "reg", "open_price": "46.1300", "close_price": "46.0620"}, {"high_price": "47.0000", "interpolated": false, "low_price": "46.9700", "begins_at": "2017-11-01T00:00:00Z", "volume": 212, "session": "reg", "open_price": "46.9700", "close_price": "47.0000"}, {"high_price": "47.0000", "interpolated": false, "low_price": "47.0000", "begins_at": "2017-11-02T00:00:00Z", "volume": 0, "session": "reg", "open_price": "47.0000", "close_price": "47.0000"}, {"high_price": "47.0000", "interpolated": false, "low_price": "47.0000", "begins_at": "2017-11-03T00:00:00Z", "volume": 0, "session": "reg", "open_price": "47.0000", "close_price": "47.0000"}, {"high_price": "47.0000", "interpolated": false, "low_price": "47.0000", "begins_at": "2017-11-06T00:00:00Z", "volume": 9, "session": "reg", "open_price": "47.0000", "close_price": "47.0000"}, {"high_price": "48.0599", "interpolated": false, "low_price": "48.0470", "begins_at": "2017-11-07T00:00:00Z", "volume": 279, "session": "reg", "open_price": "48.0599", "close_price": "48.0470"}, {"high_price": "48.0470", "interpolated": false, "low_price": "48.0470", "begins_at": "2017-11-08T00:00:00Z", "volume": 1, "session": "reg", "open_price": "48.0470", "close_price": "48.0470"}, {"high_price": "47.7300", "interpolated": false, "low_price": "47.7175", "begins_at": "2017-11-09T00:00:00Z", "volume": 776, "session": "reg", "open_price": "47.7299", "close_price": "47.7175"}, {"high_price": "47.7175", "interpolated": false, "low_price": "47.7175", "begins_at": "2017-11-10T00:00:00Z", "volume": 0, "session": "reg", "open_price": "47.7175", "close_price": "47.7175"}, {"high_price": "47.7175", "interpolated": false, "low_price": "47.7175", "begins_at": "2017-11-13T00:00:00Z", "volume": 8, "session": "reg", "open_price": "47.7175", "close_price": "47.7175"}, {"high_price": "47.7175", "interpolated": false, "low_price": "47.7175", "begins_at": "2017-11-14T00:00:00Z", "volume": 6, "session": "reg", "open_price": "47.7175", "close_price": "47.7175"}, {"high_price": "46.2004", "interpolated": false, "low_price": "45.3024", "begins_at": "2017-11-15T00:00:00Z", "volume": 571, "session": "reg", "open_price": "45.8800", "close_price": "46.2004"}, {"high_price": "46.2299", "interpolated": false, "low_price": "46.1980", "begins_at": "2017-11-16T00:00:00Z", "volume": 649, "session": "reg", "open_price": "46.2099", "close_price": "46.2299"}, {"high_price": "46.3690", "interpolated": false, "low_price": "46.3565", "begins_at": "2017-11-17T00:00:00Z", "volume": 226, "session": "reg", "open_price": "46.3565", "close_price": "46.3690"}, {"high_price": "46.3690", "interpolated": false, "low_price": "46.3690", "begins_at": "2017-11-20T00:00:00Z", "volume": 0, "session": "reg", "open_price": "46.3690", "close_price": "46.3690"}, {"high_price": "45.9500", "interpolated": false, "low_price": "45.7744", "begins_at": "2017-11-21T00:00:00Z", "volume": 367, "session": "reg", "open_price": "45.9500", "close_price": "45.7744"}, {"high_price": "46.2400", "interpolated": false, "low_price": "46.2400", "begins_at": "2017-11-22T00:00:00Z", "volume": 326, "session": "reg", "open_price": "46.2400", "close_price": "46.2400"}, {"high_price": "46.2400", "interpolated": false, "low_price": "46.2400", "begins_at": "2017-11-27T00:00:00Z", "volume": 0, "session": "reg", "open_price": "46.2400", "close_price": "46.2400"}, {"high_price": "46.2400", "interpolated": false, "low_price": "46.2400", "begins_at": "2017-11-28T00:00:00Z", "volume": 15, "session": "reg", "open_price": "46.2400", "close_price": "46.2400"}, {"high_price": "45.3499", "interpolated": false, "low_price": "45.3265", "begins_at": "2017-11-29T00:00:00Z", "volume": 831, "session": "reg", "open_price": "45.3499", "close_price": "45.3265"}, {"high_price": "46.1700", "interpolated": false, "low_price": "46.0888", "begins_at": "2017-11-30T00:00:00Z", "volume": 1071, "session": "reg", "open_price": "46.1700", "close_price": "46.0888"}, {"high_price": "47.2200", "interpolated": false, "low_price": "46.7500", "begins_at": "2017-12-01T00:00:00Z", "volume": 1020, "session": "reg", "open_price": "47.2200", "close_price": "46.7500"}, {"high_price": "46.7500", "interpolated": false, "low_price": "46.7500", "begins_at": "2017-12-04T00:00:00Z", "volume": 0, "session": "reg", "open_price": "46.7500", "close_price": "46.7500"}, {"high_price": "46.9100", "interpolated": false, "low_price": "46.8100", "begins_at": "2017-12-05T00:00:00Z", "volume": 411, "session": "reg", "open_price": "46.8100", "close_price": "46.9100"}, {"high_price": "46.2300", "interpolated": false, "low_price": "46.1800", "begins_at": "2017-12-06T00:00:00Z", "volume": 646, "session": "reg", "open_price": "46.1800", "close_price": "46.2300"}, {"high_price": "46.2300", "interpolated": false, "low_price": "46.2300", "begins_at": "2017-12-07T00:00:00Z", "volume": 0, "session": "reg", "open_price": "46.2300", "close_price": "46.2300"}, {"high_price": "47.5900", "interpolated": false, "low_price": "47.3000", "begins_at": "2017-12-08T00:00:00Z", "volume": 500, "session": "reg", "open_price": "47.3200", "close_price": "47.3900"}, {"high_price": "47.3900", "interpolated": false, "low_price": "47.3900", "begins_at": "2017-12-11T00:00:00Z", "volume": 48, "session": "reg", "open_price": "47.3900", "close_price": "47.3900"}, {"high_price": "47.3900", "interpolated": false, "low_price": "47.3900", "begins_at": "2017-12-12T00:00:00Z", "volume": 98, "session": "reg", "open_price": "47.3900", "close_price": "47.3900"}, {"high_price": "47.3900", "interpolated": false, "low_price": "47.3900", "begins_at": "2017-12-13T00:00:00Z", "volume": 50, "session": "reg", "open_price": "47.3900", "close_price": "47.3900"}, {"high_price": "47.3900", "interpolated": false, "low_price": "47.3900", "begins_at": "2017-12-14T00:00:00Z", "volume": 0, "session": "reg", "open_price": "47.3900", "close_price": "47.3900"}, {"high_price": "47.3900", "interpolated": false, "low_price": "47.3900", "begins_at": "2017-12-15T00:00:00Z", "volume": 0, "session": "reg", "open_price": "47.3900", "close_price": "47.3900"}, {"high_price": "47.3900", "interpolated": false, "low_price": "47.3900", "begins_at": "2017-12-18T00:00:00Z", "volume": 79, "session": "reg", "open_price": "47.3900", "close_price": "47.3900"}, {"high_price": "47.9754", "interpolated": false, "low_price": "47.7100", "begins_at": "2017-12-19T00:00:00Z", "volume": 1250, "session": "reg", "open_price": "47.9754", "close_price": "47.7968"}, {"high_price": "47.7968", "interpolated": false, "low_price": "47.7968", "begins_at": "2017-12-20T00:00:00Z", "volume": 0, "session": "reg", "open_price": "47.7968", "close_price": "47.7968"}, {"high_price": "48.1200", "interpolated": false, "low_price": "48.0480", "begins_at": "2017-12-21T00:00:00Z", "volume": 400, "session": "reg", "open_price": "48.1200", "close_price": "48.0480"}, {"high_price": "48.0480", "interpolated": false, "low_price": "48.0480", "begins_at": "2017-12-22T00:00:00Z", "volume": 0, "session": "reg", "open_price": "48.0480", "close_price": "48.0480"}, {"high_price": "48.8900", "interpolated": false, "low_price": "47.8300", "begins_at": "2017-12-26T00:00:00Z", "volume": 5261, "session": "reg", "open_price": "48.8500", "close_price": "48.3900"}, {"high_price": "48.8200", "interpolated": false, "low_price": "48.6760", "begins_at": "2017-12-27T00:00:00Z", "volume": 2106, "session": "reg", "open_price": "48.7005", "close_price": "48.8080"}, {"high_price": "47.9900", "interpolated": false, "low_price": "47.7060", "begins_at": "2017-12-28T00:00:00Z", "volume": 1500, "session": "reg", "open_price": "47.9900", "close_price": "47.8260"}, {"high_price": "47.7999", "interpolated": false, "low_price": "47.6771", "begins_at": "2017-12-29T00:00:00Z", "volume": 956, "session": "reg", "open_price": "47.7034", "close_price": "47.7280"}, {"high_price": "49.0850", "interpolated": false, "low_price": "48.3100", "begins_at": "2018-01-02T00:00:00Z", "volume": 3849, "session": "reg", "open_price": "48.5900", "close_price": "49.0850"}, {"high_price": "49.4250", "interpolated": false, "low_price": "49.4250", "begins_at": "2018-01-03T00:00:00Z", "volume": 110, "session": "reg", "open_price": "49.4250", "close_price": "49.4250"}, {"high_price": "49.7250", "interpolated": false, "low_price": "49.5105", "begins_at": "2018-01-04T00:00:00Z", "volume": 666, "session": "reg", "open_price": "49.5200", "close_price": "49.6386"}, {"high_price": "49.6399", "interpolated": false, "low_price": "49.6399", "begins_at": "2018-01-05T00:00:00Z", "volume": 450, "session": "reg", "open_price": "49.6399", "close_price": "49.6399"}, {"high_price": "49.6399", "interpolated": false, "low_price": "49.6399", "begins_at": "2018-01-08T00:00:00Z", "volume": 60, "session": "reg", "open_price": "49.6399", "close_price": "49.6399"}, {"high_price": "49.6399", "interpolated": false, "low_price": "49.6399", "begins_at": "2018-01-09T00:00:00Z", "volume": 166, "session": "reg", "open_price": "49.6399", "close_price": "49.6399"}, {"high_price": "49.7900", "interpolated": false, "low_price": "49.6540", "begins_at": "2018-01-10T00:00:00Z", "volume": 660, "session": "reg", "open_price": "49.6540", "close_price": "49.7150"}, {"high_price": "50.9680", "interpolated": false, "low_price": "50.2800", "begins_at": "2018-01-11T00:00:00Z", "volume": 553, "session": "reg", "open_price": "50.2800", "close_price": "50.9000"}, {"high_price": "51.0840", "interpolated": false, "low_price": "51.0840", "begins_at": "2018-01-12T00:00:00Z", "volume": 303, "session": "reg", "open_price": "51.0840", "close_price": "51.0840"}, {"high_price": "53.3200", "interpolated": false, "low_price": "51.7151", "begins_at": "2018-01-16T00:00:00Z", "volume": 870, "session": "reg", "open_price": "53.3200", "close_price": "51.7151"}, {"high_price": "51.3400", "interpolated": false, "low_price": "51.0200", "begins_at": "2018-01-17T00:00:00Z", "volume": 804, "session": "reg", "open_price": "51.0200", "close_price": "51.3400"}, {"high_price": "51.3400", "interpolated": false, "low_price": "51.3400", "begins_at": "2018-01-18T00:00:00Z", "volume": 149, "session": "reg", "open_price": "51.3400", "close_price": "51.3400"}, {"high_price": "51.2000", "interpolated": false, "low_price": "50.6500", "begins_at": "2018-01-19T00:00:00Z", "volume": 1043, "session": "reg", "open_price": "51.2000", "close_price": "50.8747"}, {"high_price": "50.8747", "interpolated": false, "low_price": "50.8747", "begins_at": "2018-01-22T00:00:00Z", "volume": 62, "session": "reg", "open_price": "50.8747", "close_price": "50.8747"}, {"high_price": "50.8747", "interpolated": false, "low_price": "50.8747", "begins_at": "2018-01-23T00:00:00Z", "volume": 35, "session": "reg", "open_price": "50.8747", "close_price": "50.8747"}, {"high_price": "52.1500", "interpolated": false, "low_price": "52.1324", "begins_at": "2018-01-24T00:00:00Z", "volume": 480, "session": "reg", "open_price": "52.1500", "close_price": "52.1324"}, {"high_price": "51.7900", "interpolated": false, "low_price": "51.7680", "begins_at": "2018-01-25T00:00:00Z", "volume": 406, "session": "reg", "open_price": "51.7899", "close_price": "51.7680"}, {"high_price": "51.7680", "interpolated": false, "low_price": "51.7680", "begins_at": "2018-01-26T00:00:00Z", "volume": 47, "session": "reg", "open_price": "51.7680", "close_price": "51.7680"}, {"high_price": "51.7680", "interpolated": false, "low_price": "51.7680", "begins_at": "2018-01-29T00:00:00Z", "volume": 0, "session": "reg", "open_price": "51.7680", "close_price": "51.7680"}, {"high_price": "50.6800", "interpolated": false, "low_price": "50.1700", "begins_at": "2018-01-30T00:00:00Z", "volume": 304, "session": "reg", "open_price": "50.6800", "close_price": "50.1700"}, {"high_price": "50.1700", "interpolated": false, "low_price": "50.1700", "begins_at": "2018-01-31T00:00:00Z", "volume": 95, "session": "reg", "open_price": "50.1700", "close_price": "50.1700"}, {"high_price": "50.1700", "interpolated": false, "low_price": "50.1700", "begins_at": "2018-02-01T00:00:00Z", "volume": 0, "session": "reg", "open_price": "50.1700", "close_price": "50.1700"}, {"high_price": "50.6700", "interpolated": false, "low_price": "50.6700", "begins_at": "2018-02-02T00:00:00Z", "volume": 313, "session": "reg", "open_price": "50.6700", "close_price": "50.6700"}, {"high_price": "50.3500", "interpolated": false, "low_price": "48.7100", "begins_at": "2018-02-05T00:00:00Z", "volume": 7014, "session": "reg", "open_price": "49.6500", "close_price": "48.7100"}, {"high_price": "49.8000", "interpolated": false, "low_price": "49.8000", "begins_at": "2018-02-06T00:00:00Z", "volume": 328, "session": "reg", "open_price": "49.8000", "close_price": "49.8000"}, {"high_price": "49.5600", "interpolated": false, "low_price": "49.5600", "begins_at": "2018-02-07T00:00:00Z", "volume": 291, "session": "reg", "open_price": "49.5600", "close_price": "49.5600"}, {"high_price": "49.2600", "interpolated": false, "low_price": "49.2600", "begins_at": "2018-02-08T00:00:00Z", "volume": 200, "session": "reg", "open_price": "49.2600", "close_price": "49.2600"}, {"high_price": "47.7900", "interpolated": false, "low_price": "47.7900", "begins_at": "2018-02-09T00:00:00Z", "volume": 200, "session": "reg", "open_price": "47.7900", "close_price": "47.7900"}, {"high_price": "47.7200", "interpolated": false, "low_price": "47.7200", "begins_at": "2018-02-12T00:00:00Z", "volume": 302, "session": "reg", "open_price": "47.7200", "close_price": "47.7200"}, {"high_price": "47.7200", "interpolated": false, "low_price": "47.7200", "begins_at": "2018-02-13T00:00:00Z", "volume": 137, "session": "reg", "open_price": "47.7200", "close_price": "47.7200"}, {"high_price": "47.9700", "interpolated": false, "low_price": "47.9700", "begins_at": "2018-02-14T00:00:00Z", "volume": 100, "session": "reg", "open_price": "47.9700", "close_price": "47.9700"}, {"high_price": "47.9700", "interpolated": false, "low_price": "47.9700", "begins_at": "2018-02-15T00:00:00Z", "volume": 0, "session": "reg", "open_price": "47.9700", "close_price": "47.9700"}, {"high_price": "47.9700", "interpolated": false, "low_price": "47.9700", "begins_at": "2018-02-16T00:00:00Z", "volume": 0, "session": "reg", "open_price": "47.9700", "close_price": "47.9700"}, {"high_price": "47.9700", "interpolated": false, "low_price": "47.9700", "begins_at": "2018-02-20T00:00:00Z", "volume": 140, "session": "reg", "open_price": "47.9700", "close_price": "47.9700"}, {"high_price": "47.9700", "interpolated": false, "low_price": "47.9700", "begins_at": "2018-02-21T00:00:00Z", "volume": 0, "session": "reg", "open_price": "47.9700", "close_price": "47.9700"}, {"high_price": "47.9700", "interpolated": false, "low_price": "47.9700", "begins_at": "2018-02-22T00:00:00Z", "volume": 0, "session": "reg", "open_price": "47.9700", "close_price": "47.9700"}, {"high_price": "47.9700", "interpolated": false, "low_price": "47.9700", "begins_at": "2018-02-23T00:00:00Z", "volume": 0, "session": "reg", "open_price": "47.9700", "close_price": "47.9700"}, {"high_price": "47.9700", "interpolated": false, "low_price": "47.9700", "begins_at": "2018-02-26T00:00:00Z", "volume": 98, "session": "reg", "open_price": "47.9700", "close_price": "47.9700"}, {"high_price": "47.9700", "interpolated": false, "low_price": "47.9700", "begins_at": "2018-02-27T00:00:00Z", "volume": 0, "session": "reg", "open_price": "47.9700", "close_price": "47.9700"}, {"high_price": "47.9700", "interpolated": false, "low_price": "47.9700", "begins_at": "2018-02-28T00:00:00Z", "volume": 0, "session": "reg", "open_price": "47.9700", "close_price": "47.9700"}, {"high_price": "47.9700", "interpolated": false, "low_price": "47.9700", "begins_at": "2018-03-01T00:00:00Z", "volume": 0, "session": "reg", "open_price": "47.9700", "close_price": "47.9700"}, {"high_price": "47.9700", "interpolated": false, "low_price": "47.9700", "begins_at": "2018-03-02T00:00:00Z", "volume": 0, "session": "reg", "open_price": "47.9700", "close_price": "47.9700"}, {"high_price": "46.3300", "interpolated": false, "low_price": "46.3300", "begins_at": "2018-03-05T00:00:00Z", "volume": 1000, "session": "reg", "open_price": "46.3300", "close_price": "46.3300"}, {"high_price": "46.3300", "interpolated": false, "low_price": "46.3300", "begins_at": "2018-03-06T00:00:00Z", "volume": 0, "session": "reg", "open_price": "46.3300", "close_price": "46.3300"}, {"high_price": "46.3300", "interpolated": false, "low_price": "46.3300", "begins_at": "2018-03-07T00:00:00Z", "volume": 0, "session": "reg", "open_price": "46.3300", "close_price": "46.3300"}, {"high_price": "46.3300", "interpolated": false, "low_price": "46.3300", "begins_at": "2018-03-08T00:00:00Z", "volume": 0, "session": "reg", "open_price": "46.3300", "close_price": "46.3300"}, {"high_price": "46.3300", "interpolated": false, "low_price": "46.3300", "begins_at": "2018-03-09T00:00:00Z", "volume": 0, "session": "reg", "open_price": "46.3300", "close_price": "46.3300"}, {"high_price": "47.1200", "interpolated": false, "low_price": "47.1068", "begins_at": "2018-03-12T00:00:00Z", "volume": 250, "session": "reg", "open_price": "47.1068", "close_price": "47.1200"}, {"high_price": "47.1200", "interpolated": false, "low_price": "47.1200", "begins_at": "2018-03-13T00:00:00Z", "volume": 0, "session": "reg", "open_price": "47.1200", "close_price": "47.1200"}, {"high_price": "47.1200", "interpolated": false, "low_price": "47.1200", "begins_at": "2018-03-14T00:00:00Z", "volume": 0, "session": "reg", "open_price": "47.1200", "close_price": "47.1200"}, {"high_price": "47.1200", "interpolated": false, "low_price": "47.1200", "begins_at": "2018-03-15T00:00:00Z", "volume": 50, "session": "reg", "open_price": "47.1200", "close_price": "47.1200"}, {"high_price": "47.1200", "interpolated": false, "low_price": "47.1200", "begins_at": "2018-03-16T00:00:00Z", "volume": 64, "session": "reg", "open_price": "47.1200", "close_price": "47.1200"}, {"high_price": "47.1200", "interpolated": false, "low_price": "47.1200", "begins_at": "2018-03-19T00:00:00Z", "volume": 50, "session": "reg", "open_price": "47.1200", "close_price": "47.1200"}, {"high_price": "44.9000", "interpolated": false, "low_price": "44.9000", "begins_at": "2018-03-20T00:00:00Z", "volume": 552, "session": "reg", "open_price": "44.9000", "close_price": "44.9000"}, {"high_price": "44.9000", "interpolated": false, "low_price": "44.9000", "begins_at": "2018-03-21T00:00:00Z", "volume": 20, "session": "reg", "open_price": "44.9000", "close_price": "44.9000"}, {"high_price": "44.9000", "interpolated": false, "low_price": "44.9000", "begins_at": "2018-03-22T00:00:00Z", "volume": 0, "session": "reg", "open_price": "44.9000", "close_price": "44.9000"}, {"high_price": "44.9000", "interpolated": false, "low_price": "44.9000", "begins_at": "2018-03-23T00:00:00Z", "volume": 0, "session": "reg", "open_price": "44.9000", "close_price": "44.9000"}, {"high_price": "44.2800", "interpolated": false, "low_price": "43.9599", "begins_at": "2018-03-26T00:00:00Z", "volume": 314, "session": "reg", "open_price": "44.2800", "close_price": "43.9600"}, {"high_price": "43.9600", "interpolated": false, "low_price": "43.9600", "begins_at": "2018-03-27T00:00:00Z", "volume": 0, "session": "reg", "open_price": "43.9600", "close_price": "43.9600"}], "bounds": "regular", "instrument": "https://api.robinhood.com/instruments/f8122a27-037e-4d17-be98-becdc737fe42/"}]