[{"span": "year", "quote": "https://api.robinhood.com/quotes/4bcb5c41-b87a-4f81-9cdd-240e1a801532/", "symbol": "FORD", "interval": "day", "historicals": [{"high_price": "1.1600", "interpolated": false, "low_price": "1.0200", "begins_at": "2017-03-28T00:00:00Z", "volume": 28786, "session": "reg", "open_price": "1.1300", "close_price": "1.0900"}, {"high_price": "1.1200", "interpolated": false, "low_price": "1.0700", "begins_at": "2017-03-29T00:00:00Z", "volume": 19413, "session": "reg", "open_price": "1.1000", "close_price": "1.1100"}, {"high_price": "1.1700", "interpolated": false, "low_price": "1.1000", "begins_at": "2017-03-30T00:00:00Z", "volume": 15795, "session": "reg", "open_price": "1.1300", "close_price": "1.1400"}, {"high_price": "1.2100", "interpolated": false, "low_price": "1.1400", "begins_at": "2017-03-31T00:00:00Z", "volume": 127244, "session": "reg", "open_price": "1.1600", "close_price": "1.1880"}, {"high_price": "1.2200", "interpolated": false, "low_price": "1.1800", "begins_at": "2017-04-03T00:00:00Z", "volume": 47627, "session": "reg", "open_price": "1.2100", "close_price": "1.1800"}, {"high_price": "1.2200", "interpolated": false, "low_price": "1.1600", "begins_at": "2017-04-04T00:00:00Z", "volume": 32671, "session": "reg", "open_price": "1.1600", "close_price": "1.1600"}, {"high_price": "1.2200", "interpolated": false, "low_price": "1.1500", "begins_at": "2017-04-05T00:00:00Z", "volume": 22047, "session": "reg", "open_price": "1.1500", "close_price": "1.1500"}, {"high_price": "1.2300", "interpolated": false, "low_price": "1.1512", "begins_at": "2017-04-06T00:00:00Z", "volume": 10253, "session": "reg", "open_price": "1.1600", "close_price": "1.1799"}, {"high_price": "1.2000", "interpolated": false, "low_price": "1.1500", "begins_at": "2017-04-07T00:00:00Z", "volume": 6879, "session": "reg", "open_price": "1.1800", "close_price": "1.1600"}, {"high_price": "1.2100", "interpolated": false, "low_price": "1.1310", "begins_at": "2017-04-10T00:00:00Z", "volume": 30841, "session": "reg", "open_price": "1.1700", "close_price": "1.1900"}, {"high_price": "1.1900", "interpolated": false, "low_price": "1.1400", "begins_at": "2017-04-11T00:00:00Z", "volume": 12941, "session": "reg", "open_price": "1.1700", "close_price": "1.1500"}, {"high_price": "1.1900", "interpolated": false, "low_price": "1.1400", "begins_at": "2017-04-12T00:00:00Z", "volume": 9608, "session": "reg", "open_price": "1.1418", "close_price": "1.1800"}, {"high_price": "1.1900", "interpolated": false, "low_price": "1.1300", "begins_at": "2017-04-13T00:00:00Z", "volume": 9532, "session": "reg", "open_price": "1.1900", "close_price": "1.1600"}, {"high_price": "1.1800", "interpolated": false, "low_price": "1.1300", "begins_at": "2017-04-17T00:00:00Z", "volume": 9547, "session": "reg", "open_price": "1.1300", "close_price": "1.1501"}, {"high_price": "1.1900", "interpolated": false, "low_price": "1.1000", "begins_at": "2017-04-18T00:00:00Z", "volume": 40609, "session": "reg", "open_price": "1.1600", "close_price": "1.1300"}, {"high_price": "1.1800", "interpolated": false, "low_price": "1.1200", "begins_at": "2017-04-19T00:00:00Z", "volume": 15387, "session": "reg", "open_price": "1.1200", "close_price": "1.1500"}, {"high_price": "1.1600", "interpolated": false, "low_price": "1.1400", "begins_at": "2017-04-20T00:00:00Z", "volume": 2429, "session": "reg", "open_price": "1.1400", "close_price": "1.1400"}, {"high_price": "1.1400", "interpolated": false, "low_price": "1.1003", "begins_at": "2017-04-21T00:00:00Z", "volume": 13842, "session": "reg", "open_price": "1.1400", "close_price": "1.1300"}, {"high_price": "1.1400", "interpolated": false, "low_price": "1.0900", "begins_at": "2017-04-24T00:00:00Z", "volume": 15657, "session": "reg", "open_price": "1.1100", "close_price": "1.1000"}, {"high_price": "1.1400", "interpolated": false, "low_price": "1.0900", "begins_at": "2017-04-25T00:00:00Z", "volume": 14173, "session": "reg", "open_price": "1.0925", "close_price": "1.1200"}, {"high_price": "1.1400", "interpolated": false, "low_price": "1.1136", "begins_at": "2017-04-26T00:00:00Z", "volume": 28125, "session": "reg", "open_price": "1.1199", "close_price": "1.1136"}, {"high_price": "1.1300", "interpolated": false, "low_price": "1.0900", "begins_at": "2017-04-27T00:00:00Z", "volume": 23057, "session": "reg", "open_price": "1.0900", "close_price": "1.0900"}, {"high_price": "1.1200", "interpolated": false, "low_price": "1.0900", "begins_at": "2017-04-28T00:00:00Z", "volume": 6720, "session": "reg", "open_price": "1.0900", "close_price": "1.1099"}, {"high_price": "1.1200", "interpolated": false, "low_price": "1.1000", "begins_at": "2017-05-01T00:00:00Z", "volume": 6157, "session": "reg", "open_price": "1.1000", "close_price": "1.1200"}, {"high_price": "1.1200", "interpolated": false, "low_price": "1.0900", "begins_at": "2017-05-02T00:00:00Z", "volume": 11491, "session": "reg", "open_price": "1.0900", "close_price": "1.1001"}, {"high_price": "1.1200", "interpolated": false, "low_price": "1.1000", "begins_at": "2017-05-03T00:00:00Z", "volume": 8914, "session": "reg", "open_price": "1.1100", "close_price": "1.1189"}, {"high_price": "1.1500", "interpolated": false, "low_price": "1.1000", "begins_at": "2017-05-04T00:00:00Z", "volume": 10561, "session": "reg", "open_price": "1.1500", "close_price": "1.1300"}, {"high_price": "1.1400", "interpolated": false, "low_price": "1.1000", "begins_at": "2017-05-05T00:00:00Z", "volume": 8134, "session": "reg", "open_price": "1.1400", "close_price": "1.1400"}, {"high_price": "1.1400", "interpolated": false, "low_price": "1.1208", "begins_at": "2017-05-08T00:00:00Z", "volume": 16878, "session": "reg", "open_price": "1.1400", "close_price": "1.1217"}, {"high_price": "1.1500", "interpolated": false, "low_price": "1.1000", "begins_at": "2017-05-09T00:00:00Z", "volume": 4925, "session": "reg", "open_price": "1.1300", "close_price": "1.1199"}, {"high_price": "1.1400", "interpolated": false, "low_price": "1.1100", "begins_at": "2017-05-10T00:00:00Z", "volume": 7937, "session": "reg", "open_price": "1.1100", "close_price": "1.1200"}, {"high_price": "1.1400", "interpolated": false, "low_price": "1.1000", "begins_at": "2017-05-11T00:00:00Z", "volume": 11186, "session": "reg", "open_price": "1.1300", "close_price": "1.1100"}, {"high_price": "1.6500", "interpolated": false, "low_price": "1.1300", "begins_at": "2017-05-12T00:00:00Z", "volume": 2017794, "session": "reg", "open_price": "1.1300", "close_price": "1.3000"}, {"high_price": "1.1800", "interpolated": false, "low_price": "1.1200", "begins_at": "2017-05-15T00:00:00Z", "volume": 140224, "session": "reg", "open_price": "1.1800", "close_price": "1.1700"}, {"high_price": "1.1800", "interpolated": false, "low_price": "1.1400", "begins_at": "2017-05-16T00:00:00Z", "volume": 49186, "session": "reg", "open_price": "1.1700", "close_price": "1.1500"}, {"high_price": "1.1500", "interpolated": false, "low_price": "1.1000", "begins_at": "2017-05-17T00:00:00Z", "volume": 82340, "session": "reg", "open_price": "1.1400", "close_price": "1.1200"}, {"high_price": "1.1200", "interpolated": false, "low_price": "1.0500", "begins_at": "2017-05-18T00:00:00Z", "volume": 59094, "session": "reg", "open_price": "1.0900", "close_price": "1.0700"}, {"high_price": "1.0900", "interpolated": false, "low_price": "1.0700", "begins_at": "2017-05-19T00:00:00Z", "volume": 51450, "session": "reg", "open_price": "1.0700", "close_price": "1.0900"}, {"high_price": "1.1100", "interpolated": false, "low_price": "1.0700", "begins_at": "2017-05-22T00:00:00Z", "volume": 59410, "session": "reg", "open_price": "1.1000", "close_price": "1.0900"}, {"high_price": "1.1373", "interpolated": false, "low_price": "1.0701", "begins_at": "2017-05-23T00:00:00Z", "volume": 36300, "session": "reg", "open_price": "1.1000", "close_price": "1.1200"}, {"high_price": "1.1400", "interpolated": false, "low_price": "1.0900", "begins_at": "2017-05-24T00:00:00Z", "volume": 26133, "session": "reg", "open_price": "1.1300", "close_price": "1.1100"}, {"high_price": "1.1400", "interpolated": false, "low_price": "1.0800", "begins_at": "2017-05-25T00:00:00Z", "volume": 28289, "session": "reg", "open_price": "1.1200", "close_price": "1.1130"}, {"high_price": "1.1300", "interpolated": false, "low_price": "1.1000", "begins_at": "2017-05-26T00:00:00Z", "volume": 4992, "session": "reg", "open_price": "1.1300", "close_price": "1.1101"}, {"high_price": "1.1373", "interpolated": false, "low_price": "1.0700", "begins_at": "2017-05-30T00:00:00Z", "volume": 19382, "session": "reg", "open_price": "1.1100", "close_price": "1.1300"}, {"high_price": "1.1100", "interpolated": false, "low_price": "1.1000", "begins_at": "2017-05-31T00:00:00Z", "volume": 10745, "session": "reg", "open_price": "1.1000", "close_price": "1.1090"}, {"high_price": "1.1300", "interpolated": false, "low_price": "1.0800", "begins_at": "2017-06-01T00:00:00Z", "volume": 11633, "session": "reg", "open_price": "1.1210", "close_price": "1.0800"}, {"high_price": "1.1249", "interpolated": false, "low_price": "1.0800", "begins_at": "2017-06-02T00:00:00Z", "volume": 16360, "session": "reg", "open_price": "1.0800", "close_price": "1.0900"}, {"high_price": "1.1263", "interpolated": false, "low_price": "1.0810", "begins_at": "2017-06-05T00:00:00Z", "volume": 10774, "session": "reg", "open_price": "1.0900", "close_price": "1.1100"}, {"high_price": "1.1040", "interpolated": false, "low_price": "1.0800", "begins_at": "2017-06-06T00:00:00Z", "volume": 11096, "session": "reg", "open_price": "1.0900", "close_price": "1.0801"}, {"high_price": "1.1100", "interpolated": false, "low_price": "1.0800", "begins_at": "2017-06-07T00:00:00Z", "volume": 5784, "session": "reg", "open_price": "1.0900", "close_price": "1.0800"}, {"high_price": "1.0974", "interpolated": false, "low_price": "1.0800", "begins_at": "2017-06-08T00:00:00Z", "volume": 7382, "session": "reg", "open_price": "1.0800", "close_price": "1.0900"}, {"high_price": "1.0995", "interpolated": false, "low_price": "1.0700", "begins_at": "2017-06-09T00:00:00Z", "volume": 27095, "session": "reg", "open_price": "1.0800", "close_price": "1.0700"}, {"high_price": "1.0883", "interpolated": false, "low_price": "1.0599", "begins_at": "2017-06-12T00:00:00Z", "volume": 41737, "session": "reg", "open_price": "1.0700", "close_price": "1.0600"}, {"high_price": "1.1000", "interpolated": false, "low_price": "1.0500", "begins_at": "2017-06-13T00:00:00Z", "volume": 23610, "session": "reg", "open_price": "1.0600", "close_price": "1.0700"}, {"high_price": "1.0900", "interpolated": false, "low_price": "1.0499", "begins_at": "2017-06-14T00:00:00Z", "volume": 12195, "session": "reg", "open_price": "1.0500", "close_price": "1.0580"}, {"high_price": "1.0716", "interpolated": false, "low_price": "1.0600", "begins_at": "2017-06-15T00:00:00Z", "volume": 6775, "session": "reg", "open_price": "1.0700", "close_price": "1.0636"}, {"high_price": "1.0900", "interpolated": false, "low_price": "1.0500", "begins_at": "2017-06-16T00:00:00Z", "volume": 6357, "session": "reg", "open_price": "1.0500", "close_price": "1.0900"}, {"high_price": "1.1300", "interpolated": false, "low_price": "1.0800", "begins_at": "2017-06-19T00:00:00Z", "volume": 16977, "session": "reg", "open_price": "1.0800", "close_price": "1.1300"}, {"high_price": "1.1000", "interpolated": false, "low_price": "1.0500", "begins_at": "2017-06-20T00:00:00Z", "volume": 6273, "session": "reg", "open_price": "1.0900", "close_price": "1.0600"}, {"high_price": "1.0900", "interpolated": false, "low_price": "1.0500", "begins_at": "2017-06-21T00:00:00Z", "volume": 6824, "session": "reg", "open_price": "1.0500", "close_price": "1.0900"}, {"high_price": "1.0792", "interpolated": false, "low_price": "1.0500", "begins_at": "2017-06-22T00:00:00Z", "volume": 4212, "session": "reg", "open_price": "1.0500", "close_price": "1.0792"}, {"high_price": "1.0600", "interpolated": false, "low_price": "1.0493", "begins_at": "2017-06-23T00:00:00Z", "volume": 26502, "session": "reg", "open_price": "1.0500", "close_price": "1.0600"}, {"high_price": "1.1200", "interpolated": false, "low_price": "1.0500", "begins_at": "2017-06-26T00:00:00Z", "volume": 58437, "session": "reg", "open_price": "1.0500", "close_price": "1.0599"}, {"high_price": "1.0800", "interpolated": false, "low_price": "1.0300", "begins_at": "2017-06-27T00:00:00Z", "volume": 18991, "session": "reg", "open_price": "1.0300", "close_price": "1.0500"}, {"high_price": "1.0900", "interpolated": false, "low_price": "1.0400", "begins_at": "2017-06-28T00:00:00Z", "volume": 9537, "session": "reg", "open_price": "1.0900", "close_price": "1.0500"}, {"high_price": "1.0668", "interpolated": false, "low_price": "1.0300", "begins_at": "2017-06-29T00:00:00Z", "volume": 10261, "session": "reg", "open_price": "1.0500", "close_price": "1.0600"}, {"high_price": "1.0699", "interpolated": false, "low_price": "1.0300", "begins_at": "2017-06-30T00:00:00Z", "volume": 18010, "session": "reg", "open_price": "1.0300", "close_price": "1.0501"}, {"high_price": "1.0600", "interpolated": false, "low_price": "1.0300", "begins_at": "2017-07-05T00:00:00Z", "volume": 29248, "session": "reg", "open_price": "1.0500", "close_price": "1.0400"}, {"high_price": "1.0900", "interpolated": false, "low_price": "1.0300", "begins_at": "2017-07-06T00:00:00Z", "volume": 27277, "session": "reg", "open_price": "1.0300", "close_price": "1.0585"}, {"high_price": "1.0900", "interpolated": false, "low_price": "1.0400", "begins_at": "2017-07-07T00:00:00Z", "volume": 6777, "session": "reg", "open_price": "1.0600", "close_price": "1.0600"}, {"high_price": "1.0754", "interpolated": false, "low_price": "1.0400", "begins_at": "2017-07-10T00:00:00Z", "volume": 17125, "session": "reg", "open_price": "1.0400", "close_price": "1.0601"}, {"high_price": "1.0838", "interpolated": false, "low_price": "1.0200", "begins_at": "2017-07-11T00:00:00Z", "volume": 63592, "session": "reg", "open_price": "1.0838", "close_price": "1.0600"}, {"high_price": "1.0800", "interpolated": false, "low_price": "1.0300", "begins_at": "2017-07-12T00:00:00Z", "volume": 15695, "session": "reg", "open_price": "1.0800", "close_price": "1.0800"}, {"high_price": "1.0800", "interpolated": false, "low_price": "1.0500", "begins_at": "2017-07-13T00:00:00Z", "volume": 4172, "session": "reg", "open_price": "1.0800", "close_price": "1.0600"}, {"high_price": "1.0800", "interpolated": false, "low_price": "1.0600", "begins_at": "2017-07-14T00:00:00Z", "volume": 20948, "session": "reg", "open_price": "1.0600", "close_price": "1.0700"}, {"high_price": "1.0900", "interpolated": false, "low_price": "1.0600", "begins_at": "2017-07-17T00:00:00Z", "volume": 12821, "session": "reg", "open_price": "1.0600", "close_price": "1.0900"}, {"high_price": "1.0800", "interpolated": false, "low_price": "1.0500", "begins_at": "2017-07-18T00:00:00Z", "volume": 31505, "session": "reg", "open_price": "1.0700", "close_price": "1.0700"}, {"high_price": "1.1400", "interpolated": false, "low_price": "1.0600", "begins_at": "2017-07-19T00:00:00Z", "volume": 99976, "session": "reg", "open_price": "1.0700", "close_price": "1.0901"}, {"high_price": "1.0900", "interpolated": false, "low_price": "1.0600", "begins_at": "2017-07-20T00:00:00Z", "volume": 26424, "session": "reg", "open_price": "1.0800", "close_price": "1.0727"}, {"high_price": "1.0900", "interpolated": false, "low_price": "1.0500", "begins_at": "2017-07-21T00:00:00Z", "volume": 20930, "session": "reg", "open_price": "1.0700", "close_price": "1.0900"}, {"high_price": "1.0900", "interpolated": false, "low_price": "1.0500", "begins_at": "2017-07-24T00:00:00Z", "volume": 18785, "session": "reg", "open_price": "1.0900", "close_price": "1.0800"}, {"high_price": "1.0800", "interpolated": false, "low_price": "1.0500", "begins_at": "2017-07-25T00:00:00Z", "volume": 19244, "session": "reg", "open_price": "1.0700", "close_price": "1.0500"}, {"high_price": "1.1700", "interpolated": false, "low_price": "1.0500", "begins_at": "2017-07-26T00:00:00Z", "volume": 239086, "session": "reg", "open_price": "1.0600", "close_price": "1.1450"}, {"high_price": "1.1300", "interpolated": false, "low_price": "1.0700", "begins_at": "2017-07-27T00:00:00Z", "volume": 55550, "session": "reg", "open_price": "1.1300", "close_price": "1.0800"}, {"high_price": "1.1300", "interpolated": false, "low_price": "1.0800", "begins_at": "2017-07-28T00:00:00Z", "volume": 36614, "session": "reg", "open_price": "1.0800", "close_price": "1.1183"}, {"high_price": "1.1200", "interpolated": false, "low_price": "1.0800", "begins_at": "2017-07-31T00:00:00Z", "volume": 16985, "session": "reg", "open_price": "1.1200", "close_price": "1.0900"}, {"high_price": "1.1200", "interpolated": false, "low_price": "1.0800", "begins_at": "2017-08-01T00:00:00Z", "volume": 17078, "session": "reg", "open_price": "1.0854", "close_price": "1.0901"}, {"high_price": "1.1000", "interpolated": false, "low_price": "1.0700", "begins_at": "2017-08-02T00:00:00Z", "volume": 9089, "session": "reg", "open_price": "1.0900", "close_price": "1.1000"}, {"high_price": "1.0900", "interpolated": false, "low_price": "1.0600", "begins_at": "2017-08-03T00:00:00Z", "volume": 27078, "session": "reg", "open_price": "1.0900", "close_price": "1.0800"}, {"high_price": "1.1000", "interpolated": false, "low_price": "1.0800", "begins_at": "2017-08-04T00:00:00Z", "volume": 21695, "session": "reg", "open_price": "1.0800", "close_price": "1.1000"}, {"high_price": "1.1000", "interpolated": false, "low_price": "1.0611", "begins_at": "2017-08-07T00:00:00Z", "volume": 11492, "session": "reg", "open_price": "1.0900", "close_price": "1.0900"}, {"high_price": "1.1200", "interpolated": false, "low_price": "1.0900", "begins_at": "2017-08-08T00:00:00Z", "volume": 9915, "session": "reg", "open_price": "1.1051", "close_price": "1.0900"}, {"high_price": "1.0900", "interpolated": false, "low_price": "1.0600", "begins_at": "2017-08-09T00:00:00Z", "volume": 10362, "session": "reg", "open_price": "1.0900", "close_price": "1.0700"}, {"high_price": "1.0800", "interpolated": false, "low_price": "1.0500", "begins_at": "2017-08-10T00:00:00Z", "volume": 14855, "session": "reg", "open_price": "1.0758", "close_price": "1.0700"}, {"high_price": "1.1100", "interpolated": false, "low_price": "1.0300", "begins_at": "2017-08-11T00:00:00Z", "volume": 44519, "session": "reg", "open_price": "1.0700", "close_price": "1.0510"}, {"high_price": "1.0900", "interpolated": false, "low_price": "1.0300", "begins_at": "2017-08-14T00:00:00Z", "volume": 71022, "session": "reg", "open_price": "1.0300", "close_price": "1.0900"}, {"high_price": "1.1872", "interpolated": false, "low_price": "1.0600", "begins_at": "2017-08-15T00:00:00Z", "volume": 103708, "session": "reg", "open_price": "1.1300", "close_price": "1.0900"}, {"high_price": "1.1200", "interpolated": false, "low_price": "1.0900", "begins_at": "2017-08-16T00:00:00Z", "volume": 47132, "session": "reg", "open_price": "1.1021", "close_price": "1.1000"}, {"high_price": "1.1000", "interpolated": false, "low_price": "1.0800", "begins_at": "2017-08-17T00:00:00Z", "volume": 22300, "session": "reg", "open_price": "1.1000", "close_price": "1.0800"}, {"high_price": "1.1000", "interpolated": false, "low_price": "1.0800", "begins_at": "2017-08-18T00:00:00Z", "volume": 1391, "session": "reg", "open_price": "1.0800", "close_price": "1.1000"}, {"high_price": "1.1000", "interpolated": false, "low_price": "1.0800", "begins_at": "2017-08-21T00:00:00Z", "volume": 15082, "session": "reg", "open_price": "1.1000", "close_price": "1.0900"}, {"high_price": "1.1200", "interpolated": false, "low_price": "1.0815", "begins_at": "2017-08-22T00:00:00Z", "volume": 12286, "session": "reg", "open_price": "1.0946", "close_price": "1.1100"}, {"high_price": "1.1200", "interpolated": false, "low_price": "1.0800", "begins_at": "2017-08-23T00:00:00Z", "volume": 36486, "session": "reg", "open_price": "1.1200", "close_price": "1.0993"}, {"high_price": "1.1000", "interpolated": false, "low_price": "1.0641", "begins_at": "2017-08-24T00:00:00Z", "volume": 51251, "session": "reg", "open_price": "1.1000", "close_price": "1.0700"}, {"high_price": "1.1400", "interpolated": false, "low_price": "1.0640", "begins_at": "2017-08-25T00:00:00Z", "volume": 62472, "session": "reg", "open_price": "1.0800", "close_price": "1.1200"}, {"high_price": "1.1700", "interpolated": false, "low_price": "1.0900", "begins_at": "2017-08-28T00:00:00Z", "volume": 101171, "session": "reg", "open_price": "1.1500", "close_price": "1.1400"}, {"high_price": "1.1424", "interpolated": false, "low_price": "1.1117", "begins_at": "2017-08-29T00:00:00Z", "volume": 58678, "session": "reg", "open_price": "1.1400", "close_price": "1.1400"}, {"high_price": "1.1400", "interpolated": false, "low_price": "1.1000", "begins_at": "2017-08-30T00:00:00Z", "volume": 26136, "session": "reg", "open_price": "1.1300", "close_price": "1.1317"}, {"high_price": "1.1600", "interpolated": false, "low_price": "1.0800", "begins_at": "2017-08-31T00:00:00Z", "volume": 124047, "session": "reg", "open_price": "1.1400", "close_price": "1.1100"}, {"high_price": "1.1600", "interpolated": false, "low_price": "1.1000", "begins_at": "2017-09-01T00:00:00Z", "volume": 54699, "session": "reg", "open_price": "1.1100", "close_price": "1.1501"}, {"high_price": "1.1700", "interpolated": false, "low_price": "1.1400", "begins_at": "2017-09-05T00:00:00Z", "volume": 53135, "session": "reg", "open_price": "1.1400", "close_price": "1.1500"}, {"high_price": "1.2000", "interpolated": false, "low_price": "1.1400", "begins_at": "2017-09-06T00:00:00Z", "volume": 60323, "session": "reg", "open_price": "1.1400", "close_price": "1.1600"}, {"high_price": "1.1900", "interpolated": false, "low_price": "1.1592", "begins_at": "2017-09-07T00:00:00Z", "volume": 7657, "session": "reg", "open_price": "1.1900", "close_price": "1.1592"}, {"high_price": "1.1896", "interpolated": false, "low_price": "1.1500", "begins_at": "2017-09-08T00:00:00Z", "volume": 44203, "session": "reg", "open_price": "1.1500", "close_price": "1.1500"}, {"high_price": "1.1800", "interpolated": false, "low_price": "1.1701", "begins_at": "2017-09-11T00:00:00Z", "volume": 22157, "session": "reg", "open_price": "1.1800", "close_price": "1.1799"}, {"high_price": "1.3500", "interpolated": false, "low_price": "1.1702", "begins_at": "2017-09-12T00:00:00Z", "volume": 328920, "session": "reg", "open_price": "1.1800", "close_price": "1.2890"}, {"high_price": "1.2645", "interpolated": false, "low_price": "1.1900", "begins_at": "2017-09-13T00:00:00Z", "volume": 83508, "session": "reg", "open_price": "1.2400", "close_price": "1.2000"}, {"high_price": "1.2200", "interpolated": false, "low_price": "1.1800", "begins_at": "2017-09-14T00:00:00Z", "volume": 45405, "session": "reg", "open_price": "1.2000", "close_price": "1.2000"}, {"high_price": "1.2000", "interpolated": false, "low_price": "1.1800", "begins_at": "2017-09-15T00:00:00Z", "volume": 12621, "session": "reg", "open_price": "1.1900", "close_price": "1.2000"}, {"high_price": "1.2300", "interpolated": false, "low_price": "1.2000", "begins_at": "2017-09-18T00:00:00Z", "volume": 26799, "session": "reg", "open_price": "1.2000", "close_price": "1.2046"}, {"high_price": "1.2200", "interpolated": false, "low_price": "1.2000", "begins_at": "2017-09-19T00:00:00Z", "volume": 18070, "session": "reg", "open_price": "1.2000", "close_price": "1.2001"}, {"high_price": "1.2100", "interpolated": false, "low_price": "1.1501", "begins_at": "2017-09-20T00:00:00Z", "volume": 31015, "session": "reg", "open_price": "1.2100", "close_price": "1.1736"}, {"high_price": "1.1700", "interpolated": false, "low_price": "1.1500", "begins_at": "2017-09-21T00:00:00Z", "volume": 20788, "session": "reg", "open_price": "1.1600", "close_price": "1.1570"}, {"high_price": "1.1800", "interpolated": false, "low_price": "1.1400", "begins_at": "2017-09-22T00:00:00Z", "volume": 29421, "session": "reg", "open_price": "1.1700", "close_price": "1.1800"}, {"high_price": "1.1800", "interpolated": false, "low_price": "1.1500", "begins_at": "2017-09-25T00:00:00Z", "volume": 9967, "session": "reg", "open_price": "1.1600", "close_price": "1.1600"}, {"high_price": "1.1578", "interpolated": false, "low_price": "1.1300", "begins_at": "2017-09-26T00:00:00Z", "volume": 28992, "session": "reg", "open_price": "1.1400", "close_price": "1.1500"}, {"high_price": "1.1800", "interpolated": false, "low_price": "1.1500", "begins_at": "2017-09-27T00:00:00Z", "volume": 15799, "session": "reg", "open_price": "1.1500", "close_price": "1.1500"}, {"high_price": "1.1999", "interpolated": false, "low_price": "1.1500", "begins_at": "2017-09-28T00:00:00Z", "volume": 31630, "session": "reg", "open_price": "1.1500", "close_price": "1.1999"}, {"high_price": "1.2290", "interpolated": false, "low_price": "1.1800", "begins_at": "2017-09-29T00:00:00Z", "volume": 10492, "session": "reg", "open_price": "1.1800", "close_price": "1.2290"}, {"high_price": "1.2100", "interpolated": false, "low_price": "1.1800", "begins_at": "2017-10-02T00:00:00Z", "volume": 18104, "session": "reg", "open_price": "1.2100", "close_price": "1.2000"}, {"high_price": "1.2000", "interpolated": false, "low_price": "1.1800", "begins_at": "2017-10-03T00:00:00Z", "volume": 17491, "session": "reg", "open_price": "1.2000", "close_price": "1.1900"}, {"high_price": "1.3000", "interpolated": false, "low_price": "1.2000", "begins_at": "2017-10-04T00:00:00Z", "volume": 280745, "session": "reg", "open_price": "1.2000", "close_price": "1.2599"}, {"high_price": "1.2590", "interpolated": false, "low_price": "1.2110", "begins_at": "2017-10-05T00:00:00Z", "volume": 22580, "session": "reg", "open_price": "1.2135", "close_price": "1.2400"}, {"high_price": "1.2500", "interpolated": false, "low_price": "1.2100", "begins_at": "2017-10-06T00:00:00Z", "volume": 24495, "session": "reg", "open_price": "1.2100", "close_price": "1.2300"}, {"high_price": "1.2400", "interpolated": false, "low_price": "1.2200", "begins_at": "2017-10-09T00:00:00Z", "volume": 18197, "session": "reg", "open_price": "1.2200", "close_price": "1.2201"}, {"high_price": "1.2500", "interpolated": false, "low_price": "1.2180", "begins_at": "2017-10-10T00:00:00Z", "volume": 6406, "session": "reg", "open_price": "1.2400", "close_price": "1.2180"}, {"high_price": "1.2400", "interpolated": false, "low_price": "1.2240", "begins_at": "2017-10-11T00:00:00Z", "volume": 7050, "session": "reg", "open_price": "1.2300", "close_price": "1.2300"}, {"high_price": "1.2300", "interpolated": false, "low_price": "1.2200", "begins_at": "2017-10-12T00:00:00Z", "volume": 3136, "session": "reg", "open_price": "1.2200", "close_price": "1.2200"}, {"high_price": "1.2200", "interpolated": false, "low_price": "1.2000", "begins_at": "2017-10-13T00:00:00Z", "volume": 6052, "session": "reg", "open_price": "1.2177", "close_price": "1.2100"}, {"high_price": "1.2300", "interpolated": false, "low_price": "1.2100", "begins_at": "2017-10-16T00:00:00Z", "volume": 14557, "session": "reg", "open_price": "1.2200", "close_price": "1.2201"}, {"high_price": "1.2363", "interpolated": false, "low_price": "1.2000", "begins_at": "2017-10-17T00:00:00Z", "volume": 9648, "session": "reg", "open_price": "1.2200", "close_price": "1.2000"}, {"high_price": "1.2300", "interpolated": false, "low_price": "1.2100", "begins_at": "2017-10-18T00:00:00Z", "volume": 21480, "session": "reg", "open_price": "1.2100", "close_price": "1.2200"}, {"high_price": "1.2700", "interpolated": false, "low_price": "1.1800", "begins_at": "2017-10-19T00:00:00Z", "volume": 22261, "session": "reg", "open_price": "1.2600", "close_price": "1.2300"}, {"high_price": "1.2500", "interpolated": false, "low_price": "1.1800", "begins_at": "2017-10-20T00:00:00Z", "volume": 30591, "session": "reg", "open_price": "1.2199", "close_price": "1.1800"}, {"high_price": "1.2300", "interpolated": false, "low_price": "1.1923", "begins_at": "2017-10-23T00:00:00Z", "volume": 22992, "session": "reg", "open_price": "1.2300", "close_price": "1.2300"}, {"high_price": "1.2440", "interpolated": false, "low_price": "1.1800", "begins_at": "2017-10-24T00:00:00Z", "volume": 57968, "session": "reg", "open_price": "1.2300", "close_price": "1.1801"}, {"high_price": "1.2000", "interpolated": false, "low_price": "1.1489", "begins_at": "2017-10-25T00:00:00Z", "volume": 47499, "session": "reg", "open_price": "1.1900", "close_price": "1.1999"}, {"high_price": "1.2000", "interpolated": false, "low_price": "1.1300", "begins_at": "2017-10-26T00:00:00Z", "volume": 11338, "session": "reg", "open_price": "1.2000", "close_price": "1.1900"}, {"high_price": "1.1900", "interpolated": false, "low_price": "1.1301", "begins_at": "2017-10-27T00:00:00Z", "volume": 19987, "session": "reg", "open_price": "1.1800", "close_price": "1.1541"}, {"high_price": "1.1712", "interpolated": false, "low_price": "1.1400", "begins_at": "2017-10-30T00:00:00Z", "volume": 20197, "session": "reg", "open_price": "1.1400", "close_price": "1.1700"}, {"high_price": "1.2000", "interpolated": false, "low_price": "1.1700", "begins_at": "2017-10-31T00:00:00Z", "volume": 21039, "session": "reg", "open_price": "1.1700", "close_price": "1.1999"}, {"high_price": "1.2000", "interpolated": false, "low_price": "1.1700", "begins_at": "2017-11-01T00:00:00Z", "volume": 38918, "session": "reg", "open_price": "1.1700", "close_price": "1.2000"}, {"high_price": "1.2200", "interpolated": false, "low_price": "1.1700", "begins_at": "2017-11-02T00:00:00Z", "volume": 23879, "session": "reg", "open_price": "1.1900", "close_price": "1.1776"}, {"high_price": "1.2500", "interpolated": false, "low_price": "1.1676", "begins_at": "2017-11-03T00:00:00Z", "volume": 61268, "session": "reg", "open_price": "1.1676", "close_price": "1.1946"}, {"high_price": "1.2400", "interpolated": false, "low_price": "1.2100", "begins_at": "2017-11-06T00:00:00Z", "volume": 15531, "session": "reg", "open_price": "1.2100", "close_price": "1.2250"}, {"high_price": "1.2300", "interpolated": false, "low_price": "1.2000", "begins_at": "2017-11-07T00:00:00Z", "volume": 45217, "session": "reg", "open_price": "1.2100", "close_price": "1.2001"}, {"high_price": "1.2500", "interpolated": false, "low_price": "1.2000", "begins_at": "2017-11-08T00:00:00Z", "volume": 27812, "session": "reg", "open_price": "1.2500", "close_price": "1.2105"}, {"high_price": "1.2200", "interpolated": false, "low_price": "1.1801", "begins_at": "2017-11-09T00:00:00Z", "volume": 13647, "session": "reg", "open_price": "1.2100", "close_price": "1.1900"}, {"high_price": "1.2500", "interpolated": false, "low_price": "1.2000", "begins_at": "2017-11-10T00:00:00Z", "volume": 44633, "session": "reg", "open_price": "1.2000", "close_price": "1.2200"}, {"high_price": "1.3400", "interpolated": false, "low_price": "1.1900", "begins_at": "2017-11-13T00:00:00Z", "volume": 98953, "session": "reg", "open_price": "1.2200", "close_price": "1.2700"}, {"high_price": "1.3054", "interpolated": false, "low_price": "1.1900", "begins_at": "2017-11-14T00:00:00Z", "volume": 58337, "session": "reg", "open_price": "1.3000", "close_price": "1.2000"}, {"high_price": "1.2600", "interpolated": false, "low_price": "1.2000", "begins_at": "2017-11-15T00:00:00Z", "volume": 35897, "session": "reg", "open_price": "1.2000", "close_price": "1.2600"}, {"high_price": "1.2800", "interpolated": false, "low_price": "1.2200", "begins_at": "2017-11-16T00:00:00Z", "volume": 27233, "session": "reg", "open_price": "1.2200", "close_price": "1.2500"}, {"high_price": "1.2800", "interpolated": false, "low_price": "1.2500", "begins_at": "2017-11-17T00:00:00Z", "volume": 42703, "session": "reg", "open_price": "1.2501", "close_price": "1.2800"}, {"high_price": "1.3125", "interpolated": false, "low_price": "1.2673", "begins_at": "2017-11-20T00:00:00Z", "volume": 32208, "session": "reg", "open_price": "1.2700", "close_price": "1.2800"}, {"high_price": "1.4800", "interpolated": false, "low_price": "1.2500", "begins_at": "2017-11-21T00:00:00Z", "volume": 349905, "session": "reg", "open_price": "1.3000", "close_price": "1.2900"}, {"high_price": "1.3561", "interpolated": false, "low_price": "1.2453", "begins_at": "2017-11-22T00:00:00Z", "volume": 38000, "session": "reg", "open_price": "1.3200", "close_price": "1.3400"}, {"high_price": "1.3899", "interpolated": false, "low_price": "1.3300", "begins_at": "2017-11-27T00:00:00Z", "volume": 35321, "session": "reg", "open_price": "1.3300", "close_price": "1.3800"}, {"high_price": "1.4001", "interpolated": false, "low_price": "1.3200", "begins_at": "2017-11-28T00:00:00Z", "volume": 51326, "session": "reg", "open_price": "1.3800", "close_price": "1.3600"}, {"high_price": "1.4000", "interpolated": false, "low_price": "1.3172", "begins_at": "2017-11-29T00:00:00Z", "volume": 18125, "session": "reg", "open_price": "1.3500", "close_price": "1.3672"}, {"high_price": "1.3700", "interpolated": false, "low_price": "1.3300", "begins_at": "2017-11-30T00:00:00Z", "volume": 24704, "session": "reg", "open_price": "1.3400", "close_price": "1.3401"}, {"high_price": "1.3700", "interpolated": false, "low_price": "1.2800", "begins_at": "2017-12-01T00:00:00Z", "volume": 59739, "session": "reg", "open_price": "1.3700", "close_price": "1.3100"}, {"high_price": "1.3300", "interpolated": false, "low_price": "1.3000", "begins_at": "2017-12-04T00:00:00Z", "volume": 14505, "session": "reg", "open_price": "1.3000", "close_price": "1.3200"}, {"high_price": "1.3300", "interpolated": false, "low_price": "1.2901", "begins_at": "2017-12-05T00:00:00Z", "volume": 12739, "session": "reg", "open_price": "1.3200", "close_price": "1.3200"}, {"high_price": "1.3200", "interpolated": false, "low_price": "1.2800", "begins_at": "2017-12-06T00:00:00Z", "volume": 4375, "session": "reg", "open_price": "1.3199", "close_price": "1.3065"}, {"high_price": "1.3099", "interpolated": false, "low_price": "1.2700", "begins_at": "2017-12-07T00:00:00Z", "volume": 22867, "session": "reg", "open_price": "1.2800", "close_price": "1.2901"}, {"high_price": "1.4000", "interpolated": false, "low_price": "1.2952", "begins_at": "2017-12-08T00:00:00Z", "volume": 69454, "session": "reg", "open_price": "1.3000", "close_price": "1.3517"}, {"high_price": "1.3700", "interpolated": false, "low_price": "1.3301", "begins_at": "2017-12-11T00:00:00Z", "volume": 28899, "session": "reg", "open_price": "1.3700", "close_price": "1.3700"}, {"high_price": "1.4000", "interpolated": false, "low_price": "1.3100", "begins_at": "2017-12-12T00:00:00Z", "volume": 54043, "session": "reg", "open_price": "1.3900", "close_price": "1.3200"}, {"high_price": "1.3800", "interpolated": false, "low_price": "1.3300", "begins_at": "2017-12-13T00:00:00Z", "volume": 15898, "session": "reg", "open_price": "1.3300", "close_price": "1.3499"}, {"high_price": "1.3500", "interpolated": false, "low_price": "1.3300", "begins_at": "2017-12-14T00:00:00Z", "volume": 56202, "session": "reg", "open_price": "1.3300", "close_price": "1.3455"}, {"high_price": "1.3617", "interpolated": false, "low_price": "1.2500", "begins_at": "2017-12-15T00:00:00Z", "volume": 155755, "session": "reg", "open_price": "1.3400", "close_price": "1.2500"}, {"high_price": "1.2700", "interpolated": false, "low_price": "1.2000", "begins_at": "2017-12-18T00:00:00Z", "volume": 28976, "session": "reg", "open_price": "1.2700", "close_price": "1.2300"}, {"high_price": "1.2600", "interpolated": false, "low_price": "1.2100", "begins_at": "2017-12-19T00:00:00Z", "volume": 49026, "session": "reg", "open_price": "1.2200", "close_price": "1.2300"}, {"high_price": "1.2868", "interpolated": false, "low_price": "1.2100", "begins_at": "2017-12-20T00:00:00Z", "volume": 67526, "session": "reg", "open_price": "1.2100", "close_price": "1.2700"}, {"high_price": "1.3000", "interpolated": false, "low_price": "1.2589", "begins_at": "2017-12-21T00:00:00Z", "volume": 43377, "session": "reg", "open_price": "1.3000", "close_price": "1.2850"}, {"high_price": "1.2900", "interpolated": false, "low_price": "1.2300", "begins_at": "2017-12-22T00:00:00Z", "volume": 29991, "session": "reg", "open_price": "1.2900", "close_price": "1.2700"}, {"high_price": "1.2800", "interpolated": false, "low_price": "1.2400", "begins_at": "2017-12-26T00:00:00Z", "volume": 12185, "session": "reg", "open_price": "1.2800", "close_price": "1.2600"}, {"high_price": "1.3200", "interpolated": false, "low_price": "1.2300", "begins_at": "2017-12-27T00:00:00Z", "volume": 30119, "session": "reg", "open_price": "1.2300", "close_price": "1.2700"}, {"high_price": "1.3100", "interpolated": false, "low_price": "1.2400", "begins_at": "2017-12-28T00:00:00Z", "volume": 26443, "session": "reg", "open_price": "1.2700", "close_price": "1.2610"}, {"high_price": "1.2800", "interpolated": false, "low_price": "1.2300", "begins_at": "2017-12-29T00:00:00Z", "volume": 45309, "session": "reg", "open_price": "1.2500", "close_price": "1.2300"}, {"high_price": "1.2800", "interpolated": false, "low_price": "1.2000", "begins_at": "2018-01-02T00:00:00Z", "volume": 77619, "session": "reg", "open_price": "1.2100", "close_price": "1.2500"}, {"high_price": "1.2600", "interpolated": false, "low_price": "1.2250", "begins_at": "2018-01-03T00:00:00Z", "volume": 29290, "session": "reg", "open_price": "1.2600", "close_price": "1.2400"}, {"high_price": "1.2800", "interpolated": false, "low_price": "1.2300", "begins_at": "2018-01-04T00:00:00Z", "volume": 21828, "session": "reg", "open_price": "1.2500", "close_price": "1.2500"}, {"high_price": "1.2800", "interpolated": false, "low_price": "1.2135", "begins_at": "2018-01-05T00:00:00Z", "volume": 68692, "session": "reg", "open_price": "1.2800", "close_price": "1.2200"}, {"high_price": "1.2600", "interpolated": false, "low_price": "1.2000", "begins_at": "2018-01-08T00:00:00Z", "volume": 16812, "session": "reg", "open_price": "1.2000", "close_price": "1.2400"}, {"high_price": "1.2500", "interpolated": false, "low_price": "1.2101", "begins_at": "2018-01-09T00:00:00Z", "volume": 50218, "session": "reg", "open_price": "1.2200", "close_price": "1.2201"}, {"high_price": "1.2600", "interpolated": false, "low_price": "1.2400", "begins_at": "2018-01-10T00:00:00Z", "volume": 45264, "session": "reg", "open_price": "1.2400", "close_price": "1.2499"}, {"high_price": "1.2500", "interpolated": false, "low_price": "1.2001", "begins_at": "2018-01-11T00:00:00Z", "volume": 54337, "session": "reg", "open_price": "1.2300", "close_price": "1.2300"}, {"high_price": "1.2300", "interpolated": false, "low_price": "1.2200", "begins_at": "2018-01-12T00:00:00Z", "volume": 23191, "session": "reg", "open_price": "1.2300", "close_price": "1.2229"}, {"high_price": "1.4500", "interpolated": false, "low_price": "1.2400", "begins_at": "2018-01-16T00:00:00Z", "volume": 634501, "session": "reg", "open_price": "1.2400", "close_price": "1.3200"}, {"high_price": "1.3300", "interpolated": false, "low_price": "1.2500", "begins_at": "2018-01-17T00:00:00Z", "volume": 41962, "session": "reg", "open_price": "1.3300", "close_price": "1.2500"}, {"high_price": "1.3100", "interpolated": false, "low_price": "1.2300", "begins_at": "2018-01-18T00:00:00Z", "volume": 169222, "session": "reg", "open_price": "1.3100", "close_price": "1.2400"}, {"high_price": "4.4500", "interpolated": false, "low_price": "2.3300", "begins_at": "2018-01-19T00:00:00Z", "volume": 58324397, "session": "reg", "open_price": "2.6000", "close_price": "2.9500"}, {"high_price": "2.8700", "interpolated": false, "low_price": "2.2801", "begins_at": "2018-01-22T00:00:00Z", "volume": 3282886, "session": "reg", "open_price": "2.6500", "close_price": "2.4900"}, {"high_price": "3.1700", "interpolated": false, "low_price": "2.3510", "begins_at": "2018-01-23T00:00:00Z", "volume": 9265675, "session": "reg", "open_price": "2.4000", "close_price": "2.9200"}, {"high_price": "3.1500", "interpolated": false, "low_price": "2.5200", "begins_at": "2018-01-24T00:00:00Z", "volume": 1779217, "session": "reg", "open_price": "2.9300", "close_price": "2.8300"}, {"high_price": "3.2800", "interpolated": false, "low_price": "2.7300", "begins_at": "2018-01-25T00:00:00Z", "volume": 3759491, "session": "reg", "open_price": "2.9000", "close_price": "2.9700"}, {"high_price": "3.2400", "interpolated": false, "low_price": "2.7200", "begins_at": "2018-01-26T00:00:00Z", "volume": 2019226, "session": "reg", "open_price": "3.0000", "close_price": "2.7400"}, {"high_price": "2.7075", "interpolated": false, "low_price": "2.4100", "begins_at": "2018-01-29T00:00:00Z", "volume": 840241, "session": "reg", "open_price": "2.6600", "close_price": "2.4900"}, {"high_price": "2.5500", "interpolated": false, "low_price": "2.3200", "begins_at": "2018-01-30T00:00:00Z", "volume": 491526, "session": "reg", "open_price": "2.4000", "close_price": "2.5200"}, {"high_price": "2.5400", "interpolated": false, "low_price": "2.3509", "begins_at": "2018-01-31T00:00:00Z", "volume": 337072, "session": "reg", "open_price": "2.4300", "close_price": "2.4300"}, {"high_price": "2.5000", "interpolated": false, "low_price": "2.3300", "begins_at": "2018-02-01T00:00:00Z", "volume": 566351, "session": "reg", "open_price": "2.3600", "close_price": "2.4100"}, {"high_price": "2.4282", "interpolated": false, "low_price": "2.0100", "begins_at": "2018-02-02T00:00:00Z", "volume": 512674, "session": "reg", "open_price": "2.3600", "close_price": "2.1200"}, {"high_price": "2.1100", "interpolated": false, "low_price": "1.9500", "begins_at": "2018-02-05T00:00:00Z", "volume": 308193, "session": "reg", "open_price": "2.0400", "close_price": "1.9700"}, {"high_price": "2.1300", "interpolated": false, "low_price": "1.8000", "begins_at": "2018-02-06T00:00:00Z", "volume": 342118, "session": "reg", "open_price": "1.9500", "close_price": "2.0499"}, {"high_price": "2.1100", "interpolated": false, "low_price": "1.9114", "begins_at": "2018-02-07T00:00:00Z", "volume": 173397, "session": "reg", "open_price": "1.9300", "close_price": "2.0300"}, {"high_price": "2.1090", "interpolated": false, "low_price": "1.9000", "begins_at": "2018-02-08T00:00:00Z", "volume": 195270, "session": "reg", "open_price": "2.0300", "close_price": "1.9200"}, {"high_price": "2.0248", "interpolated": false, "low_price": "1.8100", "begins_at": "2018-02-09T00:00:00Z", "volume": 139582, "session": "reg", "open_price": "1.9600", "close_price": "1.8900"}, {"high_price": "2.0500", "interpolated": false, "low_price": "1.8600", "begins_at": "2018-02-12T00:00:00Z", "volume": 628570, "session": "reg", "open_price": "1.8700", "close_price": "2.0400"}, {"high_price": "2.0300", "interpolated": false, "low_price": "1.9010", "begins_at": "2018-02-13T00:00:00Z", "volume": 223978, "session": "reg", "open_price": "2.0100", "close_price": "1.9600"}, {"high_price": "2.0300", "interpolated": false, "low_price": "1.9200", "begins_at": "2018-02-14T00:00:00Z", "volume": 215755, "session": "reg", "open_price": "1.9200", "close_price": "1.9900"}, {"high_price": "1.8485", "interpolated": false, "low_price": "1.7400", "begins_at": "2018-02-15T00:00:00Z", "volume": 275603, "session": "reg", "open_price": "1.7800", "close_price": "1.7600"}, {"high_price": "1.7899", "interpolated": false, "low_price": "1.6810", "begins_at": "2018-02-16T00:00:00Z", "volume": 155679, "session": "reg", "open_price": "1.7800", "close_price": "1.7200"}, {"high_price": "1.7198", "interpolated": false, "low_price": "1.6410", "begins_at": "2018-02-20T00:00:00Z", "volume": 101646, "session": "reg", "open_price": "1.6700", "close_price": "1.6800"}, {"high_price": "1.6906", "interpolated": false, "low_price": "1.6100", "begins_at": "2018-02-21T00:00:00Z", "volume": 107301, "session": "reg", "open_price": "1.6800", "close_price": "1.6300"}, {"high_price": "1.7200", "interpolated": false, "low_price": "1.6200", "begins_at": "2018-02-22T00:00:00Z", "volume": 295271, "session": "reg", "open_price": "1.6300", "close_price": "1.6700"}, {"high_price": "1.7498", "interpolated": false, "low_price": "1.6200", "begins_at": "2018-02-23T00:00:00Z", "volume": 606886, "session": "reg", "open_price": "1.7000", "close_price": "1.7100"}, {"high_price": "1.7446", "interpolated": false, "low_price": "1.6600", "begins_at": "2018-02-26T00:00:00Z", "volume": 225168, "session": "reg", "open_price": "1.7400", "close_price": "1.7000"}, {"high_price": "1.6901", "interpolated": false, "low_price": "1.5716", "begins_at": "2018-02-27T00:00:00Z", "volume": 194781, "session": "reg", "open_price": "1.6900", "close_price": "1.5900"}, {"high_price": "1.6590", "interpolated": false, "low_price": "1.5500", "begins_at": "2018-02-28T00:00:00Z", "volume": 96560, "session": "reg", "open_price": "1.5900", "close_price": "1.5700"}, {"high_price": "1.6200", "interpolated": false, "low_price": "1.4700", "begins_at": "2018-03-01T00:00:00Z", "volume": 144317, "session": "reg", "open_price": "1.5700", "close_price": "1.5600"}, {"high_price": "1.6300", "interpolated": false, "low_price": "1.5200", "begins_at": "2018-03-02T00:00:00Z", "volume": 80287, "session": "reg", "open_price": "1.5200", "close_price": "1.5600"}, {"high_price": "1.6200", "interpolated": false, "low_price": "1.5186", "begins_at": "2018-03-05T00:00:00Z", "volume": 75467, "session": "reg", "open_price": "1.5400", "close_price": "1.5700"}, {"high_price": "1.6600", "interpolated": false, "low_price": "1.5588", "begins_at": "2018-03-06T00:00:00Z", "volume": 213534, "session": "reg", "open_price": "1.5700", "close_price": "1.5700"}, {"high_price": "1.6100", "interpolated": false, "low_price": "1.5200", "begins_at": "2018-03-07T00:00:00Z", "volume": 53377, "session": "reg", "open_price": "1.5500", "close_price": "1.6000"}, {"high_price": "1.7000", "interpolated": false, "low_price": "1.5940", "begins_at": "2018-03-08T00:00:00Z", "volume": 537955, "session": "reg", "open_price": "1.6200", "close_price": "1.6600"}, {"high_price": "1.7000", "interpolated": false, "low_price": "1.5800", "begins_at": "2018-03-09T00:00:00Z", "volume": 143942, "session": "reg", "open_price": "1.6900", "close_price": "1.6200"}, {"high_price": "1.6328", "interpolated": false, "low_price": "1.5800", "begins_at": "2018-03-12T00:00:00Z", "volume": 74397, "session": "reg", "open_price": "1.6200", "close_price": "1.6000"}, {"high_price": "1.6499", "interpolated": false, "low_price": "1.5600", "begins_at": "2018-03-13T00:00:00Z", "volume": 70498, "session": "reg", "open_price": "1.6100", "close_price": "1.5600"}, {"high_price": "1.5790", "interpolated": false, "low_price": "1.5100", "begins_at": "2018-03-14T00:00:00Z", "volume": 145824, "session": "reg", "open_price": "1.5600", "close_price": "1.5200"}, {"high_price": "1.5745", "interpolated": false, "low_price": "1.4910", "begins_at": "2018-03-15T00:00:00Z", "volume": 100156, "session": "reg", "open_price": "1.5200", "close_price": "1.5000"}, {"high_price": "1.6390", "interpolated": false, "low_price": "1.4800", "begins_at": "2018-03-16T00:00:00Z", "volume": 335360, "session": "reg", "open_price": "1.5001", "close_price": "1.5500"}, {"high_price": "1.5580", "interpolated": false, "low_price": "1.4500", "begins_at": "2018-03-19T00:00:00Z", "volume": 118278, "session": "reg", "open_price": "1.5400", "close_price": "1.4700"}, {"high_price": "1.5365", "interpolated": false, "low_price": "1.4600", "begins_at": "2018-03-20T00:00:00Z", "volume": 64324, "session": "reg", "open_price": "1.4800", "close_price": "1.5200"}, {"high_price": "1.6600", "interpolated": false, "low_price": "1.4948", "begins_at": "2018-03-21T00:00:00Z", "volume": 143979, "session": "reg", "open_price": "1.5000", "close_price": "1.5400"}, {"high_price": "1.5400", "interpolated": false, "low_price": "1.4700", "begins_at": "2018-03-22T00:00:00Z", "volume": 43633, "session": "reg", "open_price": "1.5200", "close_price": "1.5200"}, {"high_price": "1.5400", "interpolated": false, "low_price": "1.4683", "begins_at": "2018-03-23T00:00:00Z", "volume": 15182, "session": "reg", "open_price": "1.5100", "close_price": "1.4900"}, {"high_price": "1.5300", "interpolated": false, "low_price": "1.4600", "begins_at": "2018-03-26T00:00:00Z", "volume": 20968, "session": "reg", "open_price": "1.5300", "close_price": "1.4700"}, {"high_price": "1.5199", "interpolated": false, "low_price": "1.4600", "begins_at": "2018-03-27T00:00:00Z", "volume": 99814, "session": "reg", "open_price": "1.4700", "close_price": "1.5199"}], "bounds": "regular", "instrument": "https://api.robinhood.com/instruments/4bcb5c41-b87a-4f81-9cdd-240e1a801532/"}]